Workbook

Sheet Свод
A1: План закупок проектного офиса «Таза Қазақстан» на IV квартал 2026 года – сверка с бюджетом (бюджет – без НДС, аутсорс – с НДС; план закупок – с НДС 16%)
A2: Проект от 14.10.2026. Бюджет – «Бюджет Таза Казахстан – октябрь–декабрь 2026 (проект 2026-10-12) v3», лист «Свод». Детализация плана – лист «IV кв. 2026».
A4: Бюджет: раздел | B4: Бюджет окт–дек 2026, ₸ без НДС | C4: План закупок окт–дек 2026, ₸ с НДС
A5: 1. Персонал: оклады и отчисления работодателя | B5: 58691748 | C5: 0
A6: 2. Аутсорс-услуги (юрист МФЦА, сис.админ, разработчик, режиссёр, копирайтер, дизайнер, менеджер по креаторам) | B6: 14567355 | C6: =SUMIF('IV кв. 2026'!M11:M90,"Аутсорс*",'IV кв. 2026'!I11:I90) -> 14567355
A7: 3. ОСНС: годовой полис на новых сотрудников | B7: 500000 | C7: =SUMIF('IV кв. 2026'!M11:M90,"ОСНС*",'IV кв. 2026'!I11:I90) -> 500000
A8: 4. Командировки по РК (в плане – авиабилеты и гостиницы) | B8: 3783804 | C8: =SUMIF('IV кв. 2026'!M11:M90,"Командировки*",'IV кв. 2026'!I11:I90) -> 2141129
A9: 5. Оснащение (разово) | B9: 29170035 | C9: =SUMIF('IV кв. 2026'!M11:M90,"Оснащение*",'IV кв. 2026'!I11:I90) -> 33262540
A10: 6. Офис: аренда, депозит, хозрасходы, курьер, интернет, обслуживание МФУ, канцелярия, представительские | B10: 17530038 | C10: =SUMIF('IV кв. 2026'!M11:M90,"Офис*",'IV кв. 2026'!I11:I90) -> 14607523
A11: 7. Цифровые инструменты | B11: 589500 | C11: =SUMIF('IV кв. 2026'!M11:M90,"Цифровые*",'IV кв. 2026'!I11:I90) -> 683820
A12: 8. Медиа: таргет, полиграфия, подписки | B12: 2525000 | C12: =SUMIF('IV кв. 2026'!M11:M90,"Медиа*",'IV кв. 2026'!I11:I90) -> 2929000
A13: Непредвиденные расходы: резерв 10% и прочие (нотариус, страхование оборудования) | B13: 12810748 | C13: =SUMIF('IV кв. 2026'!M11:M90,"Прочие*",'IV кв. 2026'!I11:I90) -> 83000
A14: Б. Первоочередные проекты | B14: 87404855 | C14: =SUMIF('IV кв. 2026'!M11:M90,"Проекты*",'IV кв. 2026'!I11:I90) -> 87404855
A15: ИТОГО | B15: =SUM(B5:B14) -> 227573083 | C15: =SUM(C5:C14) -> 156179222
A16: Проверка: сумма листа плана | C16: ='IV кв. 2026'!I91 -> 156179222

Sheet IV кв. 2026
J1: Утвержден Решением Управляющего Совета
J2: ЧФ "Central Asia Climate Foundation"
J3: Протокол № 13 от «___» октября 2026 года
A4: План закупок товаров, работ и неконсультационных услуг на IV квартал 2026 года
A5: БИН: 240240900538
A6: Наименование организации (на казахском языке): "Central Asia Climate Foundation" Жеке Қор. Наименование организации (на русском языке): Частный Фонд "Central Asia Climate Foundation"
A7: Финансовый год: 2026 год (IV квартал – октябрь–декабрь)
A8: Проект от 14.10.2026. Составлен по бюджету «Бюджет Таза Казахстан – октябрь–декабрь 2026 (проект 2026-10-12) v3». Цены и суммы – с НДС 16%; страхование – без НДС; в авиабилетах НДС включён в тариф. Способы закупок – по Правилам закупок Фонда: ЗЦП (п. 37, до 8 000 МРП), электронный магазин (гл. 8), из одного источника (п. 46), открытый конкурс (гл. 5).
A9: Приоритетность | B9: № | C9: Вид предмета закупок | D9: Наименование закупаемых товаров, работ и услуг | E9: Характеристика (описание) товаров, работ и услуг | F9: Способ закупки | G9: Объём, кол-во единиц | H9: Стоимость единицы с НДС, тенге | I9: Сумма для закупки с НДС, тенге | J9: Планируемый срок осуществления закупок (месяц) | K9: Планируемый срок поставки товара, выполнения работ, оказания услуг | L9: Место поставки товара, выполнения работ, оказания услуг | M9: Примечание (раздел бюджета, источник цены)
A10: 1 | B10: 2 | C10: 3 | D10: 4 | E10: 5 | F10: 6 | G10: 7 | H10: 8 | I10: 9 | J10: 10 | K10: 11 | L10: 12 | M10: 13
A11: 1 | B11: 1 | C11: Товар | D11: Ноутбук стандартный | E11: Core i5 / Ryzen 5, 16 ГБ ОЗУ, SSD 512 ГБ, Windows 11 Pro, гарантия 12 мес. Доставка и настройка в офисе Заказчика. | F11: ЗЦП | G11: 12 | H11: 522000 | I11: =ROUND(G11*H11,0) -> 6264000 | J11: октябрь 2026 | K11: октябрь–ноябрь 2026 | L11: Астана | M11: Оснащение
A12: 1 | B12: 2 | C12: Товар | D12: Ноутбук производительный | E12: Core i7 / Ryzen 7 и выше, 32 ГБ ОЗУ, SSD 1 ТБ, дискретная графика – руководитель департамента цифрового развития, фотограф-рилсмейкер (монтаж). | F12: ЗЦП | G12: 2 | H12: 1044000 | I12: =ROUND(G12*H12,0) -> 2088000 | J12: октябрь 2026 | K12: октябрь–ноябрь 2026 | L12: Астана | M12: Оснащение
A13: 1 | B13: 3 | C13: Товар | D13: Монитор 24" с клавиатурой, мышью и гарнитурой | E13: Комплект на рабочее место: монитор 24" IPS Full HD, проводная клавиатура и мышь, гарнитура с микрофоном. | F13: ЗЦП | G13: 10 | H13: 116000 | I13: =ROUND(G13*H13,0) -> 1160000 | J13: октябрь 2026 | K13: октябрь–ноябрь 2026 | L13: Астана | M13: Оснащение
A14: 1 | B14: 4 | C14: Товар | D14: Мебель: рабочее место (стол, кресло, тумба) | E14: Стол, эргономичное кресло, тумба. 16 рабочих мест в open space и 3 гостевых (продакшн-группа, региональные координаторы в приезд). | F14: ЗЦП | G14: 19 | H14: 232000 | I14: =ROUND(G14*H14,0) -> 4408000 | J14: октябрь 2026 | K14: октябрь–ноябрь 2026 | L14: Астана | M14: Оснащение; однородные ТРУ «мебель» ниже 8 000 МРП
A15: 1 | B15: 5 | C15: Товар | D15: Мебель кабинетов руководства | E15: Комплект на кабинет: рабочий стол, кресло, шкаф, стол для совещаний – ГИД, два заместителя, национальный координатор, финансовый директор. | F15: ЗЦП | G15: 5 | H15: 580000 | I15: =ROUND(G15*H15,0) -> 2900000 | J15: октябрь 2026 | K15: октябрь–ноябрь 2026 | L15: Астана | M15: Оснащение
A16: 1 | B16: 6 | C16: Товар | D16: Мебель переговорной | E16: Стол переговорный и 12 стульев. | F16: ЗЦП | G16: 1 | H16: 928000 | I16: =ROUND(G16*H16,0) -> 928000 | J16: октябрь 2026 | K16: октябрь–ноябрь 2026 | L16: Астана | M16: Оснащение
A17: 2 | B17: 7 | C17: Товар | D17: Стойка ресепшн | E17: Стойка ресепшн. | F17: ЗЦП | G17: 1 | H17: 290000 | I17: =ROUND(G17*H17,0) -> 290000 | J17: октябрь 2026 | K17: ноябрь 2026 | L17: Астана | M17: Оснащение
A18: 1 | B18: 8 | C18: Товар | D18: Шкафы для документов и сейф | E18: Шкафы для документов (делопроизводство, кадры, договоры) и офисный сейф для документов и печатей. | F18: ЗЦП | G18: 1 | H18: 522000 | I18: =ROUND(G18*H18,0) -> 522000 | J18: октябрь 2026 | K18: октябрь–ноябрь 2026 | L18: Астана | M18: Оснащение
A19: 2 | B19: 9 | C19: Товар | D19: Стеллажи металлические для склада и архива | E19: Стеллажи 2000×1000×500 мм, 4–5 полок: склад фото- и видеотехники, архив документов. | F19: ЗЦП | G19: 2 | H19: 69600 | I19: =ROUND(G19*H19,0) -> 139200 | J19: октябрь 2026 | K19: октябрь–ноябрь 2026 | L19: Астана | M19: Оснащение
A20: 1 | B20: 10 | C20: Услуга | D20: Сборка, доставка и подъём мебели и стеллажей | E20: Доставка, подъём на этаж и сборка рабочих мест, мебели кабинетов, переговорной, стойки ресепшн, шкафов, сейфа и стеллажей. | F20: ЗЦП | G20: 1 | H20: 918720 | I20: =ROUND(G20*H20,0) -> 918720 | J20: октябрь 2026 | K20: октябрь–ноябрь 2026 | L20: Астана | M20: Оснащение
A21: 1 | B21: 11 | C21: Товар | D21: МФУ цветное А3 | E21: Класс Kyocera TASKalfa 2554ci: печать, копирование и сканирование А3 в цвете, дуплекс, автоподатчик, сетевой и Wi-Fi модуль, тумба, доставка и установка. | F21: ЗЦП | G21: 1 | H21: 2900000 | I21: =ROUND(G21*H21,0) -> 2900000 | J21: октябрь 2026 | K21: ноябрь 2026 | L21: Астана | M21: Оснащение
A22: 1 | B22: 12 | C22: Товар | D22: Тонеры CMYK для МФУ А3 | E22: Стартовый и резервный комплекты по 4 цвета, оригинальные или рекомендованные производителем. | F22: ЗЦП | G22: 2 | H22: 348000 | I22: =ROUND(G22*H22,0) -> 696000 | J22: октябрь 2026 | K22: ноябрь 2026 | L22: Астана | M22: Оснащение
... A90: 1 | B90: 80 | C90: Услуга | D90: Авиабилеты и бронирование гостиниц (командировки) | E90: Авиабилеты и бронирование гостиниц: 14,3 поездки по РК (билет 90 000 ₸ + 2 ночи × 30 000 ₸); зарубежных командировок в 2026 году нет. | F90: ЗЦП / Из одного источника | G90: 1 | H90: 2141129 | I90: =ROUND(G90*H90,0) -> 2141129 | J90: октябрь 2026 | K90: октябрь–декабрь 2026 | L90: РК и зарубежные поездки | M90: Командировки; НДС в тарифе. Суточные и местный транспорт возмещаются по авансовому отчёту
D91: ИТОГО по плану закупок | I91: =SUM(I11:I90) -> 156179222

Sheet Цены поставщика
A1: Цены текущего поставщика канцелярских и хозяйственных товаров – ТОО «Acvee Market Astana» (b2bcompany.kz)
A2: Проверено на сайте 17.09.2026. Договор B2B22/07082025 (папка поставщика в D:\Закупки\2 Поставщики). Поставщик – на общеустановленном режиме и плательщик НДС (письмо № 10 от 20.10.2025); цены сайта совпадают с ценами счёта № AM-5960 от 08.05.2026, то есть НДС в них включён. При объёмной закупке запросить прайс со скидкой и счёт на оплату.
A4: Позиция | B4: Наименование по каталогу | C4: Цена, ₸ | D4: Единица | E4: Раздел каталога / ссылка
A5: Бумага А4 | B5: Бумага для печати "SvetoCopy Classic", А4, 80 гр/м², белая, класс C, 500 л в пачке | C5: 2450 | D5: пачка | E5: b2bcompany.kz/catalog/bumazhnaya_produktsiya/bumaga_dlya_ofisnoy_tekhniki/bumaga_ofisnaya_a4/
A6: Бумага А4 (дешевле) | B6: Бумага для печати "DELI MateCopy", А4, 80 гр/м², класс C+, 500 л в пачке | C6: 2150 | D6: пачка | E6: то же
A7: Бумага А3 | B7: Бумага для печати "SvetoCopy Classic", А3, 80 гр/м², белая, класс C, 500 л в пачке | C7: 5990 | D7: пачка | E7: b2bcompany.kz/catalog/bumazhnaya_produktsiya/bumaga_dlya_ofisnoy_tekhniki/bumaga_ofisnaya_a3/
A8: Блок для флипчарта | B8: Блок бумаги для флипчарта "Kuvert", 60×90 см, 20 л, 80 гр/м² – от; "Berlingo", 64×96 см, 20 л – 4 090 ₸ | C8: 2155 | D8: блок | E8: b2bcompany.kz/catalog/sredstva_dlya_prezentatsii/bloki_bumagi_dlya_flipchartov/
A9: Ручка шариковая | B9: Ручка шариковая "Staff Basic Budjet BP-02" / "OfficeSpace LC" – от | C9: 35 | D9: шт. | E9: b2bcompany.kz/catalog/kantselyariya_dlya_ofisa/pismennye_prinadlezhnosti/ruchki_sharikovye/
A10: Стикеры | B10: Бумага для заметок "Sticky", 76×76 мм, 100 л, клеевой край | C10: 190 | D10: блок | E10: b2bcompany.kz/catalog/bumazhnaya_produktsiya/bumaga_dlya_zametok/bumaga_dlya_zametok_s_kleevym_kraem/
A11: Папка-регистратор | B11: Папка-регистратор "Kuvert", А4, 72 мм, боковой карман | C11: 1019 | D11: шт. | E11: b2bcompany.kz/catalog/kantselyariya_dlya_ofisa/papki/papki_registratory/
A12: Файл-вкладыш А4 | B12: Файл-вкладыш "Kuvert" / "OfficeSpace", А4, 25–30 мкм, перфорация | C12: 14 | D12: шт. | E12: b2bcompany.kz/catalog/kantselyariya_dlya_ofisa/papki/fayly_vkladyshi/
A13: Батарейки АА | B13: Батарейки "Varta Superlife", LR6, АА, 4 шт. – 889 ₸; "Eleven", 4 шт. – от | C13: 680 | D13: упаковка | E13: b2bcompany.kz/catalog/ofisnaya_tekhnika_i_aksessuary/batareyki_i_zaryadnye_ustroystva/batareyki_aa/
A14: Туалетная бумага | B14: Туалетная бумага "Белоснежка", 2 слоя, 23 м – 270 ₸; "Карина", 1 слой – от | C14: 165 | D14: рулон | E14: b2bcompany.kz/catalog/khozyaystvennye_tovary/gigienicheskie_tovary_1/tualetnaya_bumaga/
A15: Бумажные полотенца | B15: Бумажные полотенца "Sunpaper Professional", 2 слоя, 2 рулона в упаковке | C15: 560 | D15: упаковка | E15: b2bcompany.kz/catalog/khozyaystvennye_tovary/gigienicheskie_tovary_1/bumazhnye_polotentsa/
A16: Жидкое мыло | B16: Жидкое мыло "Vega", 500 мл, с дозатором | C16: 661 | D16: шт. | E16: b2bcompany.kz/catalog/khozyaystvennye_tovary/mylo/mylo_zhidkoe_1/
... A18: Универсальное моющее средство | B18: Универсальное моющее средство "Yarko", 5 л – 3 395 ₸; "Mr.Proper", Лимон, 5 л – 8 335 ₸ | C18: 3395 | D18: канистра 5 л | E18: b2bcompany.kz/catalog/khozyaystvennye_tovary/bytovaya_khimiya/universalnoe_moyushchee_sredstvo/
