Workbook
Name Авиа_межд: #REF!
Name Авиа_межд: #REF!
Name Авиа_межд: #REF!
Name Авиа_межд: #REF!
Name Авиа_межд: #REF!
Name Авиа_межд: #REF!
Name Авиа_межд: Параметры!$B$25
Name Авиа_РК: #REF!
Name Авиа_РК: #REF!
Name Авиа_РК: #REF!
Name Авиа_РК: #REF!
Name Авиа_РК: #REF!
Name Авиа_РК: #REF!
Name Авиа_РК: Параметры!$B$18
Name Аренда_депозит: #REF!
Name Аренда_депозит: #REF!
Name Аренда_депозит: #REF!
Name Аренда_депозит: #REF!
Name Аренда_депозит: #REF!
Name Аренда_депозит: #REF!
Name Аренда_депозит: Параметры!$B$48
Name Аренда_мес: #REF!
Name Аренда_мес: #REF!
Name Аренда_мес: #REF!
Name Аренда_мес: #REF!
Name Аренда_мес: #REF!
Name Аренда_мес: #REF!
Name Аренда_мес: Параметры!$B$32
Name Аренда_мес_2026: #REF!
Name Аренда_мес_2026: #REF!
Name Аренда_мес_2026: #REF!
Name Аренда_мес_2026: #REF!
Name Аренда_мес_2026: #REF!
Name Аренда_мес_2026: #REF!
Name Аренда_мес_2026: Параметры!$B$49
Name Аренда_с_НДС: #REF!
Name Аренда_с_НДС: #REF!
Name Аренда_с_НДС: #REF!
Name Аренда_с_НДС: #REF!
Name Аренда_с_НДС: #REF!
Name Аренда_с_НДС: #REF!
Name Аренда_с_НДС: Параметры!$B$47
Name Депозит_мес: #REF!
Name Депозит_мес: #REF!
Name Депозит_мес: #REF!
Name Депозит_мес: #REF!
Name Депозит_мес: #REF!
Name Депозит_мес: #REF!
Name Депозит_мес: Параметры!$B$33
Name Дней_межд: #REF!
Name Дней_межд: #REF!
Name Дней_межд: #REF!
Name Дней_межд: #REF!
Name Дней_межд: #REF!
Name Дней_межд: #REF!
Name Дней_межд: Параметры!$B$28
Name Дней_РК: #REF!
Name Дней_РК: #REF!
Name Дней_РК: #REF!
Name Дней_РК: #REF!

Sheet Свод
A1: Бюджет ЦАКФ на ноябрь 2026 – февраль 2027 года, ₸
A3: Статья | B3: Октябрь-ноябрь 2026 | C3: Декабрь 2026 | D3: Январь 2027 | E3: Февраль 2027 | F3: Итого ноябрь 2026 – февраль 2027
A4: Штатная численность, чел. | B4: =SUMPRODUCT((Штат!$E$5:$E$36="штат")*Штат!$G$5:$G$36*(Штат!$I$5:$I$36<=2)) -> 22 | C4: =SUMPRODUCT((Штат!$E$5:$E$36="штат")*Штат!$G$5:$G$36*(Штат!$I$5:$I$36<=3)) -> 23 | D4: =SUMPRODUCT((Штат!$E$5:$E$36="штат")*Штат!$G$5:$G$36*(Штат!$I$5:$I$36<=3)) -> 23 | E4: =D4+COUNT('Февраль 2027'!D4:D10) -> 30
A5: в т.ч. проектный офис «Таза Қазақстан», чел. | F5: =Штат!G38 -> 15
A6: 1. Оплата труда и отчисления работодателя | B6: =(SUMPRODUCT((Штат!$E$5:$E$36="штат")*Штат!$K$5:$K$36*(Штат!$I$5:$I$36<=2)))+B7+Обязательства_ЗП -> 56312240 | C6: =(SUMPRODUCT((Штат!$E$5:$E$36="штат")*Штат!$K$5:$K$36*(Штат!$I$5:$I$36<=3)))+C7+C20 -> 37571650 | D6: =(SUMPRODUCT((Штат!$E$5:$E$36="штат")*Штат!$K$5:$K$36*(Штат!$I$5:$I$36<=3)))+D7+D20 -> 28182130 | E6: =D6+'Февраль 2027'!F11 -> 34985400 | F6: =SUM(B6:E6) -> 157051420
A7: 1а. Премия 8 работникам проектного офиса по итогам работы в октябре (1 оклад с отчислениями, выплата в декабре) | B7: 0 | C7: =Штат!$H$44 -> 9389520 | D7: 0 | E7: 0 | F7: =SUM(B7:E7) -> 9389520
A8: 2. Аутсорс-услуги: юрист МФЦА, сис.админ, разработчик, режиссёр, копирайтер, социолог, менеджер по креаторам (с НДС исполнителя) | B8: =SUMPRODUCT(Аутсорс!$I$4:$I$10*((Аутсорс!$J$4:$J$10<=1)+(Аутсорс!$J$4:$J$10<=2))) -> 6881596 | C8: =SUMPRODUCT(Аутсорс!$I$4:$I$10*(Аутсорс!$J$4:$J$10<=3)) -> 6881596 | D8: =SUMPRODUCT(Аутсорс!$I$4:$I$10*(Аутсорс!$J$4:$J$10<=3)) -> 6881596 | E8: =D8 -> 6881596 | F8: =SUM(B8:E8) -> 27526384
A9: 3. ОСНС: годовой полис на новых сотрудников | B9: =Штат!$N$37 -> 645095.24 | C9: 0 | D9: 0 | E9: ='Февраль 2027'!F23 -> 205000 | F9: =SUM(B9:E9) -> 850095.24
A10: 4. Командировки по РК | B10: =Командировки!$G$12/2 -> 1899506.2 | C10: =Командировки!$G$12/2 -> 1899506.2 | D10: =SUMPRODUCT(Командировки!$C$5:$C$11*(Командировки!$D$5:$D$11/12*Поездка_РК+Командировки!$E$5:$E$11*Поездка_местн)) -> 1958850 | E10: =D10+'Февраль 2027'!F24 -> 2554912.5 | F10: =SUM(B10:E10) -> 8312775
A11: 5. Оснащение (разово): ноутбуки, мебель, МФУ, интерактивная панель, ИБП, фото-видео, сеть | B11: =SUMIFS('Оснащение и офис'!$J$5:$J$77,'Оснащение и офис'!$A$5:$A$77,"Оснащение") -> 12336434 | C11: =SUMIFS('Оснащение и офис'!$K$5:$K$77,'Оснащение и офис'!$A$5:$A$77,"Оснащение") -> 1695609 | D11: =SUMIFS('Оснащение и офис'!$L$5:$L$77,'Оснащение и офис'!$A$5:$A$77,"Оснащение") -> 0 | E11: ='Февраль 2027'!F19 -> 505594 | F11: =SUM(B11:E11) -> 14537637
A12: 6. Офис: аренда, депозит, текущие хозрасходы, курьер, интернет, обслуживание МФУ, канцелярия, представительские, нотариус и услуги МФЦА, расчёты с поставщиками за прошлые периоды | B12: =SUMIFS('Оснащение и офис'!$J$5:$J$77,'Оснащение и офис'!$A$5:$A$77,"Офис")+Обязательства_прочие -> 12661707 | C12: =SUMIFS('Оснащение и офис'!$K$5:$K$77,'Оснащение и офис'!$A$5:$A$77,"Офис") -> 5212743.1 | D12: =SUMIFS('Оснащение и офис'!$L$5:$L$77,'Оснащение и офис'!$A$5:$A$77,"Офис") -> 5212743.1 | E12: =D12 -> 5212743.1 | F12: =SUM(B12:E12) -> 28299936
A13: 7. Цифровые инструменты | B13: =SUMIFS('Оснащение и офис'!$J$5:$J$77,'Оснащение и офис'!$A$5:$A$77,"Цифровые") -> 332947 | C13: =SUMIFS('Оснащение и офис'!$K$5:$K$77,'Оснащение и офис'!$A$5:$A$77,"Цифровые") -> 253500 | D13: =SUMIFS('Оснащение и офис'!$L$5:$L$77,'Оснащение и офис'!$A$5:$A$77,"Цифровые") -> 253500 | E13: =D13+'Февраль 2027'!F22 -> 302500 | F13: =SUM(B13:E13) -> 1142447
A14: 8. Медиа: таргет, полиграфия, подписки | B14: =SUMIFS('Оснащение и офис'!$J$5:$J$77,'Оснащение и офис'!$A$5:$A$77,"Медиа") -> 1175000 | C14: =SUMIFS('Оснащение и офис'!$K$5:$K$77,'Оснащение и офис'!$A$5:$A$77,"Медиа") -> 1175000 | D14: =SUMIFS('Оснащение и офис'!$L$5:$L$77,'Оснащение и офис'!$A$5:$A$77,"Медиа") -> 1175000 | E14: =D14 -> 1175000 | F14: =SUM(B14:E14) -> 4700000
A15: Прямые затраты | B15: =SUM(B6:B14)-B7 -> 92244525 | C15: =SUM(C6:C14)-C7 -> 54689604 | D15: =SUM(D6:D14)-D7 -> 43663819 | E15: =SUM(E6:E14)-E7 -> 51822746 | F15: =SUM(B15:E15) -> 2.4242069e+08
A16: Резерв 10% на непредвиденные расходы | B16: =(B15-Обязательства_ЗП-Обязательства_прочие-'Оснащение и офис'!$J$76)*Резерв -> 6179952.5 | C16: =(C15-C20-'Оснащение и офис'!$K$76)*Резерв -> 5468960.4 | D16: =(D15-D20-'Оснащение и офис'!$L$76)*Резерв -> 4366381.9 | E16: =(E15-E20)*Резерв -> 5182274.6 | F16: =SUM(B16:E16) -> 21197569
A17: НДС: 16% на закупки, аренду, услуги, подписки и первоочередные проекты; расчёты с бюджетом по НДС | B17: =((B11+B12+B13+B14)-Обязательства_прочие-'Оснащение и офис'!$J$59-'Оснащение и офис'!$J$76)*(1+Резерв)*НДС+Обязательства_НДС+B19*НДС -> 17136024 | C17: =((C11+C12+C13+C14)-'Оснащение и офис'!$K$59-'Оснащение и офис'!$K$76)*(1+Резерв)*НДС+C19*НДС -> 6560273.7 | D17: =((D11+D12+D13+D14)-'Оснащение и офис'!$L$59-'Оснащение и офис'!$L$76)*(1+Резерв)*НДС+D19*НДС -> 3914006.5 | E17: =(E11+E12+E13+E14)*(1+Резерв)*НДС+E19*НДС -> 5918964.4 | F17: =SUM(B17:E17) -> 33529269
A18: А. ИТОГО организационное обеспечение | B18: =B15+B16+B17 -> 1.155605e+08 | C18: =C15+C16+C17 -> 66718838 | D18: =D15+D16+D17 -> 51944208 | E18: =E15+E16+E17 -> 62923985 | F18: =SUM(B18:E18) -> 2.9714753e+08
A19: Б. Первоочередные проекты (лист «Проекты») | B19: =Проекты!$H$13 -> 38245973 | C19: =Проекты!$I$13 -> 31831173 | D19: =Проекты!$J$13 -> 17157173 | E19: ='Февраль 2027'!F25 -> 29078107 | F19: =SUM(B19:E19) -> 1.1631243e+08
A20: В. Обязательства по оплате труда и налогам за июль–октябрь 2026 | B20: =Обязательства_ЗП+Обязательства_НДС+Обязательства_прочие -> 37450000 | C20: 0 | D20: 0 | E20: 0 | F20: =SUM(B20:E20) -> 37450000
A21: ВСЕГО (А + Б) | B21: =B18+B19 -> 1.5380648e+08 | C21: =C18+C19 -> 98550012 | D21: =D18+D19 -> 69101381 | E21: =E18+E19 -> 92002091 | F21: =F18+F19 -> 4.1345996e+08
A23: Нарастающим итогом | B23: =B21 -> 1.5380648e+08 | C23: =B23+C21 -> 2.5235649e+08 | D23: =C23+D21 -> 3.2145787e+08 | E23: =D23+E21 -> 4.1345996e+08
A24: Финансирование | F24: 250000000
A25: Разница с 250 млн (+ остаток / − дефицит) | B25: =$F$24-B23 -> 96193524 | C25: =$F$24-C23 -> -2356487.3 | D25: =$F$24-D23 -> -71457868 | E25: =$F$24-E23 -> -1.6345996e+08 | F25: =F24-F21 -> -1.6345996e+08

Sheet Параметры
A1: Параметры расчёта (меняйте значения в колонке B — всё пересчитается)
A3: Имя | B3: Значение | C3: Пояснение
A4: МЗП | B4: 85000 | C4: МЗП 2026, ₸
A5: МРП | B5: 4325 | C5: МРП 2026, ₸
A6: Ставка_СН | B6: 0.06 | C6: Социальный налог — 6% (НК с 01.01.2026), база: оклад − ОПВ 10% − ВОСМС 2%
A7: Ставка_ОПВР | B7: 0.035 | C7: Пенсионные взносы работодателя — 3,5% (2026)
A8: Ставка_СО | B8: 0.05 | C8: Социальные отчисления — 5%, база до 7 МЗП
A9: Кап_СО | B9: 7 | C9: Предел базы СО, в МЗП
A10: Ставка_ООСМС | B10: 0.03 | C10: Отчисления на ОСМС работодателя — 3%
A11: Кап_ООСМС | B11: 40 | C11: Предел базы ООСМС, в МЗП (с 01.01.2026 предел вырос с 10 до 40 МЗП — изм. в Закон РК "Об обязательном соц. мед. страховании"; было 10 МЗП — это предел до 2025 г.)
A12: Ставка_ОПВ | B12: 0.1 | C12: ОПВ работника 10% — удерживается из оклада (для базы СН и СО)
A13: Ставка_ВОСМС | B13: 0.02 | C13: ВОСМС работника 2% — удерживается из оклада
A14: ОСНС | B14: 28000 | C14: ОСНС на штатного сотрудника в год, ₸
A15: ОСНС_полис | B15: =ROUND(0.29%*12*SUMIFS(Штат!$H$5:$H$36,Штат!$E$5:$E$36,"штат",Штат!$F$5:$F$36,"новая"),-3) -> 713000 | C15: Годовой полис ОСНС на новых сотрудников 2026 года: 0,29% от их годового ФОТ (тариф по КП сентября 2026), ₸
A16: Курс | B16: 530 | C16: ₸ за 1 $
A17: Сут_РК | B17: 2 | C17: Суточные по РК, МРП в день (норма 2 МРП/день — п.3 Правил, утв. пост. Правительства РК от 11.05.2018 № 256, с изм. от 29.12.2018 № 934; было 6 МРП — это порог необлагаемости суточных по ст.319 НК РК, а не норма возмещения)
A18: Авиа_РК | B18: 90000 | C18: Авиабилет Астана — областной центр, туда-обратно, ₸
A19: Отель_РК | B19: 30000 | C19: Гостиница в регионе, ₸ за ночь
A20: Трансп_РК | B20: 15000 | C20: Местный транспорт в поездке, ₸
A21: Дней_РК | B21: 3 | C21: Длительность типовой поездки по РК, дней
A22: Ночей_РК | B22: 2 | C22: Ночей в типовой поездке
A23: Поездка_РК | B23: =Авиа_РК+Отель_РК*Ночей_РК+Сут_РК*МРП*Дней_РК+Трансп_РК -> 190950 | C23: Одна поездка по РК на человека, ₸
A24: Поездка_местн | B24: =Трансп_РК+Сут_РК*МРП -> 23650 | C24: Выезд регионального координатора внутри макрорегиона (1 день), ₸
A25: Авиа_межд | B25: 900 | C25: Международный перелёт эконом, $
A26: Отель_межд | B26: 150 | C26: Гостиница за рубежом, $ за ночь
A27: Сут_межд | B27: 150 | C27: Суточные за рубежом, $ в день
A28: Дней_межд | B28: 5 | C28: Длительность загранпоездки, дней
A29: Ночей_межд | B29: 4 | C29: Ночей
A30: Страх_межд | B30: 50 | C30: Страховка/виза, $
A31: Поездка_межд | B31: =(Авиа_межд+Отель_межд*Ночей_межд+Сут_межд*Дней_межд+Страх_межд)*Курс -> 1219000 | C31: Одна загранпоездка на человека, ₸
A32: Аренда_мес | B32: =Площадь_офиса*Ставка_аренды_м2+Коммун_мес+Парковка_мест*Парковка_цена -> 4869152.1 | C32: Аренда офисов с коммунальными и парковкой, ₸ в месяц без НДС (БЦ «Сыганак», 7 этаж: 701–702 + зона 710 – расчёт ниже)
A33: Депозит_мес | B33: 1 | C33: Гарантийный депозит по аренде, в месячных ставках (возвратный)
A34: Резерв | B34: 0.1 | C34: Резерв на непредвиденные расходы (10% — по требованию, было 5%)
A35: НДС | B35: 0.16 | C35: НДС 16% — для аутсорса (ТОО — плательщик НДС) и справочно для договора услуг
A37: Период: октябрь–декабрь 2026 (3 мес.).
A38: Старт позиции/расхода: 1 – октябрь, 2 – ноябрь, 3 – декабрь 2026.
A41: Аренда – БЦ «Сыганак», ул. Сыганак, 70, 7 этаж: 701–702 + зона 710
A42: Площадь_офиса | B42: =ROUND((52.2+21.4+12.4+33.7+190)*1.1,2) -> 340.67 | C42: Площадь к оплате, м²: 701 (52,2) + 701а (21,4) + 701б (12,4) + 702 (33,7) = 119,7 по плану БЦ; зона 710 – 190,0 по экспликации БЦ; итого 309,7 полезной + 10% мест общего пользования
A43: Ставка_аренды_м2 | B43: 13500 | C43: Ставка аренды со скидкой, ₸ за 1 м² в месяц без НДС и без коммунальных (условия БЦ от 22.09.2026)
A44: Коммун_мес | B44: =743*309.7 -> 230107.1 | C44: Коммунальные, ₸ в месяц без НДС: 743 ₸/м² × 309,7 м² полезной площади (без МОП)
A45: Парковка_мест | B45: 1 | C45: Парковка – 1 платное место. БЦ предоставляет одно место бесплатно, в расчёте остаётся одно платное
A46: Парковка_цена | B46: 40000 | C46: Парковка, ₸ за 1 место в месяц без НДС – 40 000, уточнено у БЦ
A47: Аренда_с_НДС | B47: =Аренда_мес*(1+НДС) -> 5648216.4 | C47: Справочно: аренда с коммунальными и парковкой, ₸ в месяц с НДС 16%
A48: Аренда_депозит | B48: =Аренда_мес*Депозит_мес -> 4869152.1 | C48: Справочно: гарантийный депозит (возвратный), ₸
A49: Аренда_мес_2026 | B49: =11/31+2 -> 2.3548387 | C49: Месяцев аренды в 2026: 11 дней октября + ноябрь + декабрь ≈ 2,35 мес.
A50: Оснащение офиса
A51: Сборка_мебели_проц | B51: 0.1 | C51: Сборка, доставка и подъём мебели — доля от стоимости мебели
A52: Мес_2026_новые | B52: 2 | C52: Месяцев 2026 для новых сотрудников (зарплата, отчисления): приём с 01.11.2026, 2 мес. Действующие – 3 мес. Аренда – с 21.10.2026 (Аренда_мес_2026)
A54: Обязательства Фонда на 01.11.2026 (погашение в ноябре)
A55: Обязательства_ЗП | B55: 29613000 | C55: Оплата труда за июль–октябрь 2026 с налогами – в строке «Оплата труда»
A56: Обязательства_НДС | B56: 7355000 | C56: Обязательства по НДС – в строке НДС
A57: Обязательства_прочие | B57: 482000 | C57: Прочие обязательства – в строке «Офис» (без резерва и НДС)

Sheet Штат
A1: Штатная структура ЦАКФ и проектного офиса «Таза Қазақстан» и расходы на персонал, ₸
A4: № | B4: Блок | C4: Должность | D4: Подчиняется | E4: Форма | F4: Статус | G4: Кол-во | H4: Оклад за ед., гросс в мес. (аутсорс — без НДС) | I4: Старт (1 – октябрь, 2 – ноябрь, 3 – декабрь) | J4: Отчисления работодателя / НДС на ед. в мес. | K4: Стоимость строки в мес. | L4: Мес. 2026 (новые – с 01.11) | M4: ФОТ+отчисл. окт–дек 2026 | N4: ОСНС (годовой полис новым сотрудникам) | O4: Итого окт–дек 2026 | P4: Функционал и опыт | Q4: Премия за октябрь (1 – да)
A5: 1 | B5: ЦАКФ — руководство Фонда | C5: Главный исполнительный директор (ГИД) | D5: — | E5: штат | F5: действующий | G5: 1 | H5: 1600000 | I5: 2 | J5: =IF(E5="штат",ROUND(Ставка_СН*H5*(1-Ставка_ОПВ-Ставка_ВОСМС)+Ставка_ОПВР*H5+Ставка_СО*MIN(H5*(1-Ставка_ОПВ),Кап_СО*МЗП)+Ставка_ООСМС*MIN(H5,Кап_ООСМС*МЗП),0),ROUND(H5*НДС,0)) -> 218230 | K5: =G5*(H5+J5) -> 1818230 | L5: =IF(AND(F5="новая",I5=1),Мес_2026_новые,MAX(0,4-I5)) -> 2 | M5: =K5*L5 -> 3636460 | N5: =IF(AND(E5="штат",F5="новая"),ОСНС_полис*G5/COUNTIFS($E$5:$E$36,"штат",$F$5:$F$36,"новая"),0) -> 0 | O5: =M5+N5 -> 3636460 | P5: [Қаражан Е.Н.] Общее руководство Фондом и проектным офисом, руководство Проектным офисом для Центральной Азии, соглашение с МЭПР, отчётность перед органами Фонда. Опыт: к.э.н. (PhD), MSc LSE («Болашақ»), Chevening; ГИД ЦАКФ с 02.2025 (Региональный экологический саммит 2026); председатель Правления ИЭИ, советник Министра национальной экономики, консультант АБР, директор по устойчивому развитию ФНБ «Самрук-Қазына».
A6: 2 | B6: ЦАКФ — руководство Фонда | C6: Советник ГИД по стратегии и науке | D6: ГИД | E6: штат | F6: действующий | G6: 1 | H6: 1400000 | I6: 2 | J6: =IF(E6="штат",ROUND(Ставка_СН*H6*(1-Ставка_ОПВ-Ставка_ВОСМС)+Ставка_ОПВР*H6+Ставка_СО*MIN(H6*(1-Ставка_ОПВ),Кап_СО*МЗП)+Ставка_ООСМС*MIN(H6,Кап_ООСМС*МЗП),0),ROUND(H6*НДС,0)) -> 194670 | K6: =G6*(H6+J6) -> 1594670 | L6: =IF(AND(F6="новая",I6=1),Мес_2026_новые,MAX(0,4-I6)) -> 2 | M6: =K6*L6 -> 3189340 | N6: =IF(AND(E6="штат",F6="новая"),ОСНС_полис*G6/COUNTIFS($E$5:$E$36,"штат",$F$5:$F$36,"новая"),0) -> 0 | O6: =M6+N6 -> 3189340 | P6: [Кононец А.В.] Стратегия и научное направление Фонда, аналитические и экспертные материалы, международные партнёры; поручения ГИД. Опыт: 20 лет в медиа и госкоммуникациях – руководитель пресс-службы, советник министра труда и социальной защиты, главный редактор Казправды, Total.kz и др.; в ЦАКФ с 07.2025.
A7: 3 | B7: ЦАКФ — руководство Фонда | C7: Заместитель ГИД (адм.-хоз. вопросы, закупки, кадры, проекты) | D7: ГИД | E7: штат | F7: действующий | G7: 1 | H7: 1400000 | I7: 2 | J7: =IF(E7="штат",ROUND(Ставка_СН*H7*(1-Ставка_ОПВ-Ставка_ВОСМС)+Ставка_ОПВР*H7+Ставка_СО*MIN(H7*(1-Ставка_ОПВ),Кап_СО*МЗП)+Ставка_ООСМС*MIN(H7,Кап_ООСМС*МЗП),0),ROUND(H7*НДС,0)) -> 194670 | K7: =G7*(H7+J7) -> 1594670 | L7: =IF(AND(F7="новая",I7=1),Мес_2026_новые,MAX(0,4-I7)) -> 2 | M7: =K7*L7 -> 3189340 | N7: =IF(AND(E7="штат",F7="новая"),ОСНС_полис*G7/COUNTIFS($E$5:$E$36,"штат",$F$5:$F$36,"новая"),0) -> 0 | O7: =M7+N7 -> 3189340 | P7: [Темирбеков М.Е.] Наём, закупки, офис, договоры с поставщиками. Опыт: международные экономические отношения (диплом с отличием); акиматы Костанайской области и Астаны; руководитель аппарата холдинга (3 000+ сотрудников); проекты МЗ РК и Всемирного банка; руководитель в общественных организациях, структур в квазигоссекторе; в ЦАКФ с 02.2025, член Управляющего совета.
A8: 4 | B8: Проектный офис — руководство | C8: Руководитель проектного офиса «Таза Қазақстан» | D8: ГИД | E8: штат | F8: новая | G8: 1 | H8: 1400000 | I8: 2 | J8: =IF(E8="штат",ROUND(Ставка_СН*H8*(1-Ставка_ОПВ-Ставка_ВОСМС)+Ставка_ОПВР*H8+Ставка_СО*MIN(H8*(1-Ставка_ОПВ),Кап_СО*МЗП)+Ставка_ООСМС*MIN(H8,Кап_ООСМС*МЗП),0),ROUND(H8*НДС,0)) -> 194670 | K8: =G8*(H8+J8) -> 1594670 | L8: =IF(AND(F8="новая",I8=1),Мес_2026_новые,MAX(0,4-I8)) -> 2 | M8: =K8*L8 -> 3189340 | N8: =IF(AND(E8="штат",F8="новая"),ОСНС_полис*G8/COUNTIFS($E$5:$E$36,"штат",$F$5:$F$36,"новая"),0) -> 33952.381 | O8: =M8+N8 -> 3223292.4 | P8: [Серикжанова Айгерим] Руководитель проектного офиса: руководство командой, календарь мероприятий, работа с акиматами и госорганами. Опыт: директор Департамента развития талантов, образовательных программ и экспертного сопровождения КФ «Фонд развития креативных индустрий»; PhD, постдокторантура «Политология» (ЕНУ им. Л.Н. Гумилёва), магистр права LLM (РУДН), магистр юридических наук (КазНУ им. аль-Фараби). | Q8: 1
A9: 6 | B9: Департамент социологических исследований и аналитики | C9: Руководитель департамента | D9: Руководителю проектного офиса «Таза Қазақстан» | E9: штат | F9: новая | G9: 1 | H9: 1300000 | I9: 3 | J9: =IF(E9="штат",ROUND(Ставка_СН*H9*(1-Ставка_ОПВ-Ставка_ВОСМС)+Ставка_ОПВР*H9+Ставка_СО*MIN(H9*(1-Ставка_ОПВ),Кап_СО*МЗП)+Ставка_ООСМС*MIN(H9,Кап_ООСМС*МЗП),0),ROUND(H9*НДС,0)) -> 182890 | K9: =G9*(H9+J9) -> 1482890 | L9: =IF(AND(F9="новая",I9=1),Мес_2026_новые,MAX(0,4-I9)) -> 1 | M9: =K9*L9 -> 1482890 | N9: =IF(AND(E9="штат",F9="новая"),ОСНС_полис*G9/COUNTIFS($E$5:$E$36,"штат",$F$5:$F$36,"новая"),0) -> 33952.381 | O9: =M9+N9 -> 1516842.4 | P9: [Өміртай А.] Руководитель департамента социологии: программа исследований, методология измерения поведения, ежегодный доклад
A10: 6 | B10: Департамент социологических исследований и аналитики | C10: Главный специалист — аналитик | D10: Руководителю департамента | E10: штат | F10: новая | G10: 1 | H10: 1000000 | I10: 2 | J10: =IF(E10="штат",ROUND(Ставка_СН*H10*(1-Ставка_ОПВ-Ставка_ВОСМС)+Ставка_ОПВР*H10+Ставка_СО*MIN(H10*(1-Ставка_ОПВ),Кап_СО*МЗП)+Ставка_ООСМС*MIN(H10,Кап_ООСМС*МЗП),0),ROUND(H10*НДС,0)) -> 147550 | K10: =G10*(H10+J10) -> 1147550 | L10: =IF(AND(F10="новая",I10=1),Мес_2026_новые,MAX(0,4-I10)) -> 2 | M10: =K10*L10 -> 2295100 | N10: =IF(AND(E10="штат",F10="новая"),ОСНС_полис*G10/COUNTIFS($E$5:$E$36,"штат",$F$5:$F$36,"новая"),0) -> 33952.381 | O10: =M10+N10 -> 2329052.4 | P10: [Абенов Алибек] Аналитик: большие данные, дашборды, расчёт KPI, аналитическое сопровождение проектов. Опыт: руководитель управления развития кадров и документооборота АО «Центр международных программ»; бакалавр «Метрология, стандартизация и сертификация» (Карагандинский экономический университет). | Q10: 1
A11: 6 | B11: Департамент социологических исследований и аналитики | C11: Социолог — аутсорс | D11: Руководителю департамента | E11: аутсорс | F11: новая | G11: 0 | H11: 700000 | I11: 2 | J11: =IF(E11="штат",ROUND(Ставка_СН*H11*(1-Ставка_ОПВ-Ставка_ВОСМС)+Ставка_ОПВР*H11+Ставка_СО*MIN(H11*(1-Ставка_ОПВ),Кап_СО*МЗП)+Ставка_ООСМС*MIN(H11,Кап_ООСМС*МЗП),0),ROUND(H11*НДС,0)) -> 112000 | K11: =G11*(H11+J11) -> 0 | L11: =IF(AND(F11="новая",I11=1),Мес_2026_новые,MAX(0,4-I11)) -> 2 | M11: =K11*L11 -> 0 | N11: =IF(AND(E11="штат",F11="новая"),ОСНС_полис*G11/COUNTIFS($E$5:$E$36,"штат",$F$5:$F$36,"новая"),0) -> 0 | O11: =M11+N11 -> 0 | P11: [Нурканат А.] Социолог (аутсорс): опросы, полевые работы, обработка данных
A12: 6 | B12: Департамент социологических исследований и аналитики | C12: Главный специалист — социолог | D12: Руководителю департамента | E12: штат | F12: новая | G12: 1 | H12: 1000000 | I12: 2 | J12: =IF(E12="штат",ROUND(Ставка_СН*H12*(1-Ставка_ОПВ-Ставка_ВОСМС)+Ставка_ОПВР*H12+Ставка_СО*MIN(H12*(1-Ставка_ОПВ),Кап_СО*МЗП)+Ставка_ООСМС*MIN(H12,Кап_ООСМС*МЗП),0),ROUND(H12*НДС,0)) -> 147550 | K12: =G12*(H12+J12) -> 1147550 | L12: =IF(AND(F12="новая",I12=1),Мес_2026_новые,MAX(0,4-I12)) -> 2 | M12: =K12*L12 -> 2295100 | N12: =IF(AND(E12="штат",F12="новая"),ОСНС_полис*G12/COUNTIFS($E$5:$E$36,"штат",$F$5:$F$36,"новая"),0) -> 33952.381 | O12: =M12+N12 -> 2329052.4 | P12: [Тленчиева Ш.] Исследования восприятия акции, опросы. Опыт: PhD по социологии.
A13: 14 | B13: Департамент проектного управления и региональной координации | C13: Заместитель директора (МЭПР, ЦГО, регионы) | D13: Директору департамента | E13: штат | F13: новая | G13: 1 | H13: 1100000 | I13: 2 | J13: =IF(E13="штат",ROUND(Ставка_СН*H13*(1-Ставка_ОПВ-Ставка_ВОСМС)+Ставка_ОПВР*H13+Ставка_СО*MIN(H13*(1-Ставка_ОПВ),Кап_СО*МЗП)+Ставка_ООСМС*MIN(H13,Кап_ООСМС*МЗП),0),ROUND(H13*НДС,0)) -> 159330 | K13: =G13*(H13+J13) -> 1259330 | L13: =IF(AND(F13="новая",I13=1),Мес_2026_новые,MAX(0,4-I13)) -> 2 | M13: =K13*L13 -> 2518660 | N13: =IF(AND(E13="штат",F13="новая"),ОСНС_полис*G13/COUNTIFS($E$5:$E$36,"штат",$F$5:$F$36,"новая"),0) -> 33952.381 | O13: =M13+N13 -> 2552612.4 | P13: Взаимодействие с МЭПР, ЦГО и регионами
A14: 15 | B14: Департамент проектного управления и региональной координации | C14: Главный специалист | D14: Директору департамента | E14: штат | F14: новая | G14: 1 | H14: 1000000 | I14: 2 | J14: =IF(E14="штат",ROUND(Ставка_СН*H14*(1-Ставка_ОПВ-Ставка_ВОСМС)+Ставка_ОПВР*H14+Ставка_СО*MIN(H14*(1-Ставка_ОПВ),Кап_СО*МЗП)+Ставка_ООСМС*MIN(H14,Кап_ООСМС*МЗП),0),ROUND(H14*НДС,0)) -> 147550 | K14: =G14*(H14+J14) -> 1147550 | L14: =IF(AND(F14="новая",I14=1),Мес_2026_новые,MAX(0,4-I14)) -> 2 | M14: =K14*L14 -> 2295100 | N14: =IF(AND(E14="штат",F14="новая"),ОСНС_полис*G14/COUNTIFS($E$5:$E$36,"штат",$F$5:$F$36,"новая"),0) -> 33952.381 | O14: =M14+N14 -> 2329052.4 | P14: [Қуандық Жасұлан] Проектный менеджер: ведение проектов, координация регионов, молодёжные проекты. Опыт: президент благотворительного фонда «Dauletten», основатель портала для молодёжи jastar.online; КазНУ им. аль-Фараби – бакалавр «Государственное и местное управление», MBA, докторантура (PhD). | Q14: 1
A15: 17 | B15: Департамент проектного управления и региональной координации | C15: Главный специалист | D15: Директору департамента | E15: штат | F15: новая | G15: 1 | H15: 1000000 | I15: 2 | J15: =IF(E15="штат",ROUND(Ставка_СН*H15*(1-Ставка_ОПВ-Ставка_ВОСМС)+Ставка_ОПВР*H15+Ставка_СО*MIN(H15*(1-Ставка_ОПВ),Кап_СО*МЗП)+Ставка_ООСМС*MIN(H15,Кап_ООСМС*МЗП),0),ROUND(H15*НДС,0)) -> 147550 | K15: =G15*(H15+J15) -> 1147550 | L15: =IF(AND(F15="новая",I15=1),Мес_2026_новые,MAX(0,4-I15)) -> 2 | M15: =K15*L15 -> 2295100 | N15: =IF(AND(E15="штат",F15="новая"),ОСНС_полис*G15/COUNTIFS($E$5:$E$36,"штат",$F$5:$F$36,"новая"),0) -> 33952.381 | O15: =M15+N15 -> 2329052.4 | P15: [Жандилдаев Бакдаулет] Проектный менеджер: координация регионов, взаимодействие с госорганами и общественными организациями. Опыт: исполнительный директор ОЮЛ «Конгресс молодежи Казахстана»; бакалавр «Государственное и местное управление» (КазУТБ), «Финансы» (Тұран-Астана), магистр юриспруденции («Синергия»). | Q15: 1
A16: 18 | B16: Департамент проектного управления и региональной координации | C16: Ведущий специалист | D16: Директору департамента | E16: штат | F16: новая | G16: 1 | H16: 1000000 | I16: 2 | J16: =IF(E16="штат",ROUND(Ставка_СН*H16*(1-Ставка_ОПВ-Ставка_ВОСМС)+Ставка_ОПВР*H16+Ставка_СО*MIN(H16*(1-Ставка_ОПВ),Кап_СО*МЗП)+Ставка_ООСМС*MIN(H16,Кап_ООСМС*МЗП),0),ROUND(H16*НДС,0)) -> 147550 | K16: =G16*(H16+J16) -> 1147550 | L16: =IF(AND(F16="новая",I16=1),Мес_2026_новые,MAX(0,4-I16)) -> 2 | M16: =K16*L16 -> 2295100 | N16: =IF(AND(E16="штат",F16="новая"),ОСНС_полис*G16/COUNTIFS($E$5:$E$36,"штат",$F$5:$F$36,"новая"),0) -> 33952.381 | O16: =M16+N16 -> 2329052.4 | P16: [Шербаева Бибинур] Проектный менеджер: ведение проектов календаря, планы и отчёты, взаимодействие с акиматами. Опыт: председатель ОСО «За будущее Казахстана»; бакалавр «Профессиональное обучение», магистр «Казахский язык и литература» (Казахский национальный женский педагогический университет). | Q16: 1
A17: 19 | B17: Департамент проектного управления и региональной координации | C17: Главный специалист | D17: Директору департамента | E17: штат | F17: новая | G17: 0 | H17: 1000000 | I17: 3 | J17: =IF(E17="штат",ROUND(Ставка_СН*H17*(1-Ставка_ОПВ-Ставка_ВОСМС)+Ставка_ОПВР*H17+Ставка_СО*MIN(H17*(1-Ставка_ОПВ),Кап_СО*МЗП)+Ставка_ООСМС*MIN(H17,Кап_ООСМС*МЗП),0),ROUND(H17*НДС,0)) -> 147550 | K17: =G17*(H17+J17) -> 0 | L17: =IF(AND(F17="новая",I17=1),Мес_2026_новые,MAX(0,4-I17)) -> 1 | M17: =K17*L17 -> 0 | N17: =IF(AND(E17="штат",F17="новая"),ОСНС_полис*G17/COUNTIFS($E$5:$E$36,"штат",$F$5:$F$36,"новая"),0) -> 0 | O17: =M17+N17 -> 0 | P17: [Арманов Р.] Ведение проектов и закреплённых регионов, мониторинг мероприятий
A18: 19 | B18: Департамент проектного управления и региональной координации | C18: Ведущий специалист | D18: Директору департамента | E18: штат | F18: новая | G18: 0 | H18: 700000 | I18: 3 | J18: =IF(E18="штат",ROUND(Ставка_СН*H18*(1-Ставка_ОПВ-Ставка_ВОСМС)+Ставка_ОПВР*H18+Ставка_СО*MIN(H18*(1-Ставка_ОПВ),Кап_СО*МЗП)+Ставка_ООСМС*MIN(H18,Кап_ООСМС*МЗП),0),ROUND(H18*НДС,0)) -> 112210 | K18: =G18*(H18+J18) -> 0 | L18: =IF(AND(F18="новая",I18=1),Мес_2026_новые,MAX(0,4-I18)) -> 1 | M18: =K18*L18 -> 0 | N18: =IF(AND(E18="штат",F18="новая"),ОСНС_полис*G18/COUNTIFS($E$5:$E$36,"штат",$F$5:$F$36,"новая"),0) -> 0 | O18: =M18+N18 -> 0 | P18: [Мирам А.] Ведение проектов и закреплённых регионов, сбор данных
A19: 19 | B19: Департамент проектного управления и региональной координации | C19: Ведущий специалист | D19: Директору департамента | E19: штат | F19: новая | G19: 1 | H19: 700000 | I19: 2 | J19: =IF(E19="штат",ROUND(Ставка_СН*H19*(1-Ставка_ОПВ-Ставка_ВОСМС)+Ставка_ОПВР*H19+Ставка_СО*MIN(H19*(1-Ставка_ОПВ),Кап_СО*МЗП)+Ставка_ООСМС*MIN(H19,Кап_ООСМС*МЗП),0),ROUND(H19*НДС,0)) -> 112210 | K19: =G19*(H19+J19) -> 812210 | L19: =IF(AND(F19="новая",I19=1),Мес_2026_новые,MAX(0,4-I19)) -> 2 | M19: =K19*L19 -> 1624420 | N19: =IF(AND(E19="штат",F19="новая"),ОСНС_полис*G19/COUNTIFS($E$5:$E$36,"штат",$F$5:$F$36,"новая"),0) -> 33952.381 | O19: =M19+N19 -> 1658372.4 | P19: [Тулесова А.] Ведение проектов и закреплённых регионов, мониторинг мероприятий, отчётность
A20: 23 | B20: Департамент цифрового развития | C20: Руководитель департамента | D20: Руководителю проектного офиса «Таза Қазақстан» | E20: штат | F20: новая | G20: 1 | H20: 1300000 | I20: 2 | J20: =IF(E20="штат",ROUND(Ставка_СН*H20*(1-Ставка_ОПВ-Ставка_ВОСМС)+Ставка_ОПВР*H20+Ставка_СО*MIN(H20*(1-Ставка_ОПВ),Кап_СО*МЗП)+Ставка_ООСМС*MIN(H20,Кап_ООСМС*МЗП),0),ROUND(H20*НДС,0)) -> 182890 | K20: =G20*(H20+J20) -> 1482890 | L20: =IF(AND(F20="новая",I20=1),Мес_2026_новые,MAX(0,4-I20)) -> 2 | M20: =K20*L20 -> 2965780 | N20: =IF(AND(E20="штат",F20="новая"),ОСНС_полис*G20/COUNTIFS($E$5:$E$36,"штат",$F$5:$F$36,"новая"),0) -> 33952.381 | O20: =M20+N20 -> 2999732.4 | P20: [Тастан Нұрбол] IT-специалист: платформа TAZA.KZ, цифровой мониторинг, информационная безопасность, работа с подрядчиком платформы. Опыт: советник председателя по информационной безопасности НАО «ННПЦ Тіл-Қазына»; бакалавр «Вычислительная техника и программное обеспечение» (ЕНУ им. Л.Н. Гумилёва), магистр юриспруденции. | Q20: 1
A21: 24 | B21: Департамент цифрового развития | C21: Разработчик (ИИ, ГИС), платформа — аутсорс | D21: Руководителю департамента | E21: аутсорс | F21: новая | G21: 0 | H21: 1000000 | I21: 2 | J21: =IF(E21="штат",ROUND(Ставка_СН*H21*(1-Ставка_ОПВ-Ставка_ВОСМС)+Ставка_ОПВР*H21+Ставка_СО*MIN(H21*(1-Ставка_ОПВ),Кап_СО*МЗП)+Ставка_ООСМС*MIN(H21,Кап_ООСМС*МЗП),0),ROUND(H21*НДС,0)) -> 160000 | K21: =G21*(H21+J21) -> 0 | L21: =IF(AND(F21="новая",I21=1),Мес_2026_новые,MAX(0,4-I21)) -> 2 | M21: =K21*L21 -> 0 | N21: =IF(AND(E21="штат",F21="новая"),ОСНС_полис*G21/COUNTIFS($E$5:$E$36,"штат",$F$5:$F$36,"новая"),0) -> 0 | O21: =M21+N21 -> 0 | P21: [аутсорс] Разработка и сопровождение ИИ- и ГИС-инструментов, цифровой платформы
A22: 25 | B22: Группа «Коммуникация и креатив» | C22: Руководитель группы | D22: Руководителю проектного офиса «Таза Қазақстан» | E22: штат | F22: новая | G22: 1 | H22: 1300000 | I22: 2 | J22: =IF(E22="штат",ROUND(Ставка_СН*H22*(1-Ставка_ОПВ-Ставка_ВОСМС)+Ставка_ОПВР*H22+Ставка_СО*MIN(H22*(1-Ставка_ОПВ),Кап_СО*МЗП)+Ставка_ООСМС*MIN(H22,Кап_ООСМС*МЗП),0),ROUND(H22*НДС,0)) -> 182890 | K22: =G22*(H22+J22) -> 1482890 | L22: =IF(AND(F22="новая",I22=1),Мес_2026_новые,MAX(0,4-I22)) -> 2 | M22: =K22*L22 -> 2965780 | N22: =IF(AND(E22="штат",F22="новая"),ОСНС_полис*G22/COUNTIFS($E$5:$E$36,"штат",$F$5:$F$36,"новая"),0) -> 33952.381 | O22: =M22+N22 -> 2999732.4 | P22: [Сағынұлы С.] Коммуникационная стратегия, медиаплан, работа со СМИ
A23: 26 | B23: Группа «Коммуникация и креатив» | C23: Главный специалист — PR, пресс-секретарь | D23: Руководителю группы | E23: штат | F23: новая | G23: 1 | H23: 1000000 | I23: 2 | J23: =IF(E23="штат",ROUND(Ставка_СН*H23*(1-Ставка_ОПВ-Ставка_ВОСМС)+Ставка_ОПВР*H23+Ставка_СО*MIN(H23*(1-Ставка_ОПВ),Кап_СО*МЗП)+Ставка_ООСМС*MIN(H23,Кап_ООСМС*МЗП),0),ROUND(H23*НДС,0)) -> 147550 | K23: =G23*(H23+J23) -> 1147550 | L23: =IF(AND(F23="новая",I23=1),Мес_2026_новые,MAX(0,4-I23)) -> 2 | M23: =K23*L23 -> 2295100 | N23: =IF(AND(E23="штат",F23="новая"),ОСНС_полис*G23/COUNTIFS($E$5:$E$36,"штат",$F$5:$F$36,"новая"),0) -> 33952.381 | O23: =M23+N23 -> 2329052.4 | P23: [Талғат Айман] PR-менеджер: пресс-служба, тексты и материалы для СМИ и соцсетей. Опыт: ведущий специалист КФ «Фонд развития креативных индустрий»; бакалавр журналистики (ЕНУ им. Л.Н. Гумилёва). | Q23: 1
A24: 27 | B24: Группа «Коммуникация и креатив» | C24: Режиссёр, видеограф-монтажёр — аутсорс | D24: Руководителю группы | E24: аутсорс | F24: новая | G24: 0 | H24: 1000000 | I24: 2 | J24: =IF(E24="штат",ROUND(Ставка_СН*H24*(1-Ставка_ОПВ-Ставка_ВОСМС)+Ставка_ОПВР*H24+Ставка_СО*MIN(H24*(1-Ставка_ОПВ),Кап_СО*МЗП)+Ставка_ООСМС*MIN(H24,Кап_ООСМС*МЗП),0),ROUND(H24*НДС,0)) -> 160000 | K24: =G24*(H24+J24) -> 0 | L24: =IF(AND(F24="новая",I24=1),Мес_2026_новые,MAX(0,4-I24)) -> 2 | M24: =K24*L24 -> 0 | N24: =IF(AND(E24="штат",F24="новая"),ОСНС_полис*G24/COUNTIFS($E$5:$E$36,"штат",$F$5:$F$36,"новая"),0) -> 0 | O24: =M24+N24 -> 0 | P24: [аутсорс] Съёмка и монтаж видео, ролики
A25: 28 | B25: Группа «Коммуникация и креатив» | C25: Копирайтер — аутсорс | D25: Руководителю группы | E25: аутсорс | F25: новая | G25: 0 | H25: 700000 | I25: 2 | J25: =IF(E25="штат",ROUND(Ставка_СН*H25*(1-Ставка_ОПВ-Ставка_ВОСМС)+Ставка_ОПВР*H25+Ставка_СО*MIN(H25*(1-Ставка_ОПВ),Кап_СО*МЗП)+Ставка_ООСМС*MIN(H25,Кап_ООСМС*МЗП),0),ROUND(H25*НДС,0)) -> 112000 | K25: =G25*(H25+J25) -> 0 | L25: =IF(AND(F25="новая",I25=1),Мес_2026_новые,MAX(0,4-I25)) -> 2 | M25: =K25*L25 -> 0 | N25: =IF(AND(E25="штат",F25="новая"),ОСНС_полис*G25/COUNTIFS($E$5:$E$36,"штат",$F$5:$F$36,"новая"),0) -> 0 | O25: =M25+N25 -> 0 | P25: [аутсорс] Тексты для соцсетей, сайта, СМИ
A26: 29 | B26: Группа «Коммуникация и креатив» | C26: Ведущий специалист — дизайнер | D26: Руководителю группы | E26: штат | F26: новая | G26: 1 | H26: 700000 | I26: 2 | J26: =IF(E26="штат",ROUND(Ставка_СН*H26*(1-Ставка_ОПВ-Ставка_ВОСМС)+Ставка_ОПВР*H26+Ставка_СО*MIN(H26*(1-Ставка_ОПВ),Кап_СО*МЗП)+Ставка_ООСМС*MIN(H26,Кап_ООСМС*МЗП),0),ROUND(H26*НДС,0)) -> 112210 | K26: =G26*(H26+J26) -> 812210 | L26: =IF(AND(F26="новая",I26=1),Мес_2026_новые,MAX(0,4-I26)) -> 2 | M26: =K26*L26 -> 1624420 | N26: =IF(AND(E26="штат",F26="новая"),ОСНС_полис*G26/COUNTIFS($E$5:$E$36,"штат",$F$5:$F$36,"новая"),0) -> 33952.381 | O26: =M26+N26 -> 1658372.4 | P26: [Найла] Визуалы, инфографика, макеты, фирменный стиль | Q26: 1
A27: 30 | B27: Группа «Коммуникация и креатив» | C27: Ведущий специалист — фотограф, рилсмейкер | D27: Руководителю группы | E27: штат | F27: новая | G27: 1 | H27: 1000000 | I27: 2 | J27: =IF(E27="штат",ROUND(Ставка_СН*H27*(1-Ставка_ОПВ-Ставка_ВОСМС)+Ставка_ОПВР*H27+Ставка_СО*MIN(H27*(1-Ставка_ОПВ),Кап_СО*МЗП)+Ставка_ООСМС*MIN(H27,Кап_ООСМС*МЗП),0),ROUND(H27*НДС,0)) -> 147550 | K27: =G27*(H27+J27) -> 1147550 | L27: =IF(AND(F27="новая",I27=1),Мес_2026_новые,MAX(0,4-I27)) -> 2 | M27: =K27*L27 -> 2295100 | N27: =IF(AND(E27="штат",F27="новая"),ОСНС_полис*G27/COUNTIFS($E$5:$E$36,"штат",$F$5:$F$36,"новая"),0) -> 33952.381 | O27: =M27+N27 -> 2329052.4 | P27: [Жумабай Б.] Фотосъёмка, короткие видео
A28: 31 | B28: Группа «Коммуникация и креатив» | C28: Ведущий специалист — менеджер по блогерам | D28: Руководителю группы | E28: штат | F28: новая | G28: 1 | H28: 700000 | I28: 2 | J28: =IF(E28="штат",ROUND(Ставка_СН*H28*(1-Ставка_ОПВ-Ставка_ВОСМС)+Ставка_ОПВР*H28+Ставка_СО*MIN(H28*(1-Ставка_ОПВ),Кап_СО*МЗП)+Ставка_ООСМС*MIN(H28,Кап_ООСМС*МЗП),0),ROUND(H28*НДС,0)) -> 112210 | K28: =G28*(H28+J28) -> 812210 | L28: =IF(AND(F28="новая",I28=1),Мес_2026_новые,MAX(0,4-I28)) -> 2 | M28: =K28*L28 -> 1624420 | N28: =IF(AND(E28="штат",F28="новая"),ОСНС_полис*G28/COUNTIFS($E$5:$E$36,"штат",$F$5:$F$36,"новая"),0) -> 33952.381 | O28: =M28+N28 -> 1658372.4 | P28: [Дутбаева] Работа с блогерами и лидерами мнений
A29: 32 | B29: Группа «Коммуникация и креатив» | C29: Менеджер по креаторам и креативным проектам — аутсорс | D29: Руководителю группы | E29: аутсорс | F29: новая | G29: 0 | H29: 700000 | I29: 2 | J29: =IF(E29="штат",ROUND(Ставка_СН*H29*(1-Ставка_ОПВ-Ставка_ВОСМС)+Ставка_ОПВР*H29+Ставка_СО*MIN(H29*(1-Ставка_ОПВ),Кап_СО*МЗП)+Ставка_ООСМС*MIN(H29,Кап_ООСМС*МЗП),0),ROUND(H29*НДС,0)) -> 112000 | K29: =G29*(H29+J29) -> 0 | L29: =IF(AND(F29="новая",I29=1),Мес_2026_новые,MAX(0,4-I29)) -> 2 | M29: =K29*L29 -> 0 | N29: =IF(AND(E29="штат",F29="новая"),ОСНС_полис*G29/COUNTIFS($E$5:$E$36,"штат",$F$5:$F$36,"новая"),0) -> 0 | O29: =M29+N29 -> 0 | P29: [аутсорс] Работа с креаторами, креативные проекты
A30: 33 | B30: Административный персонал | C30: Финансовый директор | D30: ГИД | E30: штат | F30: действующий | G30: 1 | H30: 1400000 | I30: 2 | J30: =IF(E30="штат",ROUND(Ставка_СН*H30*(1-Ставка_ОПВ-Ставка_ВОСМС)+Ставка_ОПВР*H30+Ставка_СО*MIN(H30*(1-Ставка_ОПВ),Кап_СО*МЗП)+Ставка_ООСМС*MIN(H30,Кап_ООСМС*МЗП),0),ROUND(H30*НДС,0)) -> 194670 | K30: =G30*(H30+J30) -> 1594670 | L30: =IF(AND(F30="новая",I30=1),Мес_2026_новые,MAX(0,4-I30)) -> 2 | M30: =K30*L30 -> 3189340 | N30: =IF(AND(E30="штат",F30="новая"),ОСНС_полис*G30/COUNTIFS($E$5:$E$36,"штат",$F$5:$F$36,"новая"),0) -> 0 | O30: =M30+N30 -> 3189340 | P30: [Оразбаева М.К.] Бюджет проекта, раздельный учёт, работа со спонсорами, финансовая отчётность, налоги. Опыт: 30+ лет в финансах, бухгалтерском и налоговом учёте – главный бухгалтер АО «Международный аэропорт Нурсултан Назарбаев», аудит BDO Qazaqstan (МФЦА); профессиональный бухгалтер РК, ДипИФР ACCA, налоговый консультант.
A31: 34 | B31: Административный персонал | C31: Бухгалтер | D31: Финансовому директору | E31: штат | F31: новая | G31: 1 | H31: 700000 | I31: 2 | J31: =IF(E31="штат",ROUND(Ставка_СН*H31*(1-Ставка_ОПВ-Ставка_ВОСМС)+Ставка_ОПВР*H31+Ставка_СО*MIN(H31*(1-Ставка_ОПВ),Кап_СО*МЗП)+Ставка_ООСМС*MIN(H31,Кап_ООСМС*МЗП),0),ROUND(H31*НДС,0)) -> 112210 | K31: =G31*(H31+J31) -> 812210 | L31: =IF(AND(F31="новая",I31=1),Мес_2026_новые,MAX(0,4-I31)) -> 2 | M31: =K31*L31 -> 1624420 | N31: =IF(AND(E31="штат",F31="новая"),ОСНС_полис*G31/COUNTIFS($E$5:$E$36,"штат",$F$5:$F$36,"новая"),0) -> 33952.381 | O31: =M31+N31 -> 1658372.4 | P31: [вакансия] Первичные документы, платежи, зарплата, авансовые отчёты, учёт основных средств
A32: 35 | B32: Проектный офис для Центральной Азии по изменению климата и зеленой энергетике | C32: Заместитель руководителя ПО для ЦА | D32: ГИД (Руководитель Проектного офиса для Центральной Азии) | E32: штат | F32: новая | G32: 1 | H32: 1000000 | I32: 2 | J32: =IF(E32="штат",ROUND(Ставка_СН*H32*(1-Ставка_ОПВ-Ставка_ВОСМС)+Ставка_ОПВР*H32+Ставка_СО*MIN(H32*(1-Ставка_ОПВ),Кап_СО*МЗП)+Ставка_ООСМС*MIN(H32,Кап_ООСМС*МЗП),0),ROUND(H32*НДС,0)) -> 147550 | K32: =G32*(H32+J32) -> 1147550 | L32: =IF(AND(F32="новая",I32=1),Мес_2026_новые,MAX(0,4-I32)) -> 2 | M32: =K32*L32 -> 2295100 | N32: =IF(AND(E32="штат",F32="новая"),ОСНС_полис*G32/COUNTIFS($E$5:$E$36,"штат",$F$5:$F$36,"новая"),0) -> 33952.381 | O32: =M32+N32 -> 2329052.4 | P32: Международные и страновые проекты Фонда
A33: 35 | B33: Проектный офис для Центральной Азии по изменению климата и зеленой энергетике | C33: Менеджер проектов | D33: ГИД (Руководитель Проектного офиса для Центральной Азии) | E33: штат | F33: новая | G33: 1 | H33: 800000 | I33: 2 | J33: =IF(E33="штат",ROUND(Ставка_СН*H33*(1-Ставка_ОПВ-Ставка_ВОСМС)+Ставка_ОПВР*H33+Ставка_СО*MIN(H33*(1-Ставка_ОПВ),Кап_СО*МЗП)+Ставка_ООСМС*MIN(H33,Кап_ООСМС*МЗП),0),ROUND(H33*НДС,0)) -> 123990 | K33: =G33*(H33+J33) -> 923990 | L33: =IF(AND(F33="новая",I33=1),Мес_2026_новые,MAX(0,4-I33)) -> 2 | M33: =K33*L33 -> 1847980 | N33: =IF(AND(E33="штат",F33="новая"),ОСНС_полис*G33/COUNTIFS($E$5:$E$36,"штат",$F$5:$F$36,"новая"),0) -> 33952.381 | O33: =M33+N33 -> 1881932.4 | P33: [Загирова Анастасия] Экологическая экспертиза, данные о состоянии окружающей среды, методические материалы
A34: 35 | B34: Проектный офис для Центральной Азии по изменению климата и зеленой энергетике | C34: Менеджер проектов | D34: ГИД (Руководитель Проектного офиса для Центральной Азии) | E34: штат | F34: новая | G34: 1 | H34: 800000 | I34: 2 | J34: =IF(E34="штат",ROUND(Ставка_СН*H34*(1-Ставка_ОПВ-Ставка_ВОСМС)+Ставка_ОПВР*H34+Ставка_СО*MIN(H34*(1-Ставка_ОПВ),Кап_СО*МЗП)+Ставка_ООСМС*MIN(H34,Кап_ООСМС*МЗП),0),ROUND(H34*НДС,0)) -> 123990 | K34: =G34*(H34+J34) -> 923990 | L34: =IF(AND(F34="новая",I34=1),Мес_2026_новые,MAX(0,4-I34)) -> 2 | M34: =K34*L34 -> 1847980 | N34: =IF(AND(E34="штат",F34="новая"),ОСНС_полис*G34/COUNTIFS($E$5:$E$36,"штат",$F$5:$F$36,"новая"),0) -> 33952.381 | O34: =M34+N34 -> 1881932.4 | P34: [Абулхан А.] Молодёжь, волонтёры, НПО, школы и вузы; экспертиза молодёжных и общественных проектов
A35: 36 | B35: Административный персонал | C35: Юрист (МФЦА) — аутсорс | D35: Заместителю ГИД (адм.-хоз.) | E35: аутсорс | F35: новая | G35: 0 | H35: 867500 | I35: 2 | J35: =IF(E35="штат",ROUND(Ставка_СН*H35*(1-Ставка_ОПВ-Ставка_ВОСМС)+Ставка_ОПВР*H35+Ставка_СО*MIN(H35*(1-Ставка_ОПВ),Кап_СО*МЗП)+Ставка_ООСМС*MIN(H35,Кап_ООСМС*МЗП),0),ROUND(H35*НДС,0)) -> 138800 | K35: =G35*(H35+J35) -> 0 | L35: =IF(AND(F35="новая",I35=1),Мес_2026_новые,MAX(0,4-I35)) -> 2 | M35: =K35*L35 -> 0 | N35: =IF(AND(E35="штат",F35="новая"),ОСНС_полис*G35/COUNTIFS($E$5:$E$36,"штат",$F$5:$F$36,"новая"),0) -> 0 | O35: =M35+N35 -> 0 | P35: [аутсорс] Договоры и соглашения, право МФЦА, сопровождение закупок и кадровых документов
A36: 37 | B36: Административный персонал | C36: Администратор (сис.админ) — аутсорс | D36: Заместителю ГИД (адм.-хоз.) | E36: аутсорс | F36: новая | G36: 0 | H36: 425600 | I36: 2 | J36: =IF(E36="штат",ROUND(Ставка_СН*H36*(1-Ставка_ОПВ-Ставка_ВОСМС)+Ставка_ОПВР*H36+Ставка_СО*MIN(H36*(1-Ставка_ОПВ),Кап_СО*МЗП)+Ставка_ООСМС*MIN(H36,Кап_ООСМС*МЗП),0),ROUND(H36*НДС,0)) -> 68096 | K36: =G36*(H36+J36) -> 0 | L36: =IF(AND(F36="новая",I36=1),Мес_2026_новые,MAX(0,4-I36)) -> 2 | M36: =K36*L36 -> 0 | N36: =IF(AND(E36="штат",F36="новая"),ОСНС_полис*G36/COUNTIFS($E$5:$E$36,"штат",$F$5:$F$36,"новая"),0) -> 0 | O36: =M36+N36 -> 0 | P36: [аутсорс] ИТ-инфраструктура, сеть и техника; делопроизводство, хоз. администрирование, ассистирование
C37: ИТОГО (штат) | G37: =SUM(G5:G36) -> 23 | H37: =SUMPRODUCT(G5:G36,H5:H36) -> 24600000 | K37: =SUM(K5:K36) -> 28182130 | M37: =SUM(M5:M36) -> 54881370 | N37: =SUM(N5:N36) -> 645095.24 | O37: =SUM(O5:O36) -> 55526465
C38: в т.ч. проектный офис | G38: =SUM(G8:G12)+SUM(G13:G29) -> 15 | H38: =SUMPRODUCT(G8:G12,H8:H12)+SUMPRODUCT(G13:G29,H13:H29) -> 15500000
C39: в т.ч. Фонд | G39: =G37-G38 -> 8 | H39: =H37-H38 -> 9100000
C41: Премия по итогам работы в октябре 2026 года (выплата в декабре)
C42: База: оклады 8 работников проектного офиса «Таза Қазақстан» (столбец Q) за один месяц, гросс | H42: =SUMPRODUCT(Q5:Q36,H5:H36) -> 8400000
C43: Отчисления работодателя на премию (ОПВР 3,5% + ООСМС 3% + СН 6% от дохода за вычетом ОПВ и ВОСМС) | H43: =H42*(Ставка_ОПВР+Ставка_ООСМС+Ставка_СН*(1-Ставка_ОПВ-Ставка_ВОСМС)) -> 989520
C44: ИТОГО премия с отчислениями работодателя | H44: =H42+H43 -> 9389520
C45: Социальные отчисления на премию не добавлены: по большинству окладов предел базы (7 МЗП) выбран самим окладом. По низким окладам бухгалтерия добавит СО – ставка отчислений вырастет с 11,78% до 16%.

Sheet Аутсорс
A1: Аутсорс-услуги: расчёт на октябрь–декабрь 2026 года, ₸
A3: № | B3: Позиция | C3: Подчиняется | D3: Функции | E3: Ставка в мес. без НДС | F3: Вознаграждение Antal 10%, ₸/мес | G3: Стоимость с вознаграждением, ₸/мес без НДС | H3: НДС 16% | I3: В мес. с НДС | J3: Старт (1 – октябрь, 2 – ноябрь, 3 – декабрь) | K3: Мес. 2026 | L3: Окт–дек 2026
A4: 1 | B4: Юрист (МФЦА), на руки 700 000 | C4: Заместителю ГИД (адм.-хоз.) | D4: Договоры и соглашения, право МФЦА, сопровождение закупок и кадровых документов | E4: 867500 | F4: =ROUND(E4*'Комиссия Antal'!$B$4,0) -> 86750 | G4: =E4+F4 -> 954250 | H4: =ROUND(G4*НДС,0) -> 152680 | I4: =G4+H4 -> 1106930 | J4: 2 | K4: =IF(J4=1,Мес_2026_новые,MAX(0,4-J4)) -> 2 | L4: =I4*K4 -> 2213860
A5: 2 | B5: Администратор (сис.админ), на руки 350 000 | C5: Заместителю ГИД (адм.-хоз.) | D5: ИТ-инфраструктура, сеть и техника; делопроизводство, хоз. администрирование, ассистирование | E5: 425600 | F5: =ROUND(E5*'Комиссия Antal'!$B$4,0) -> 42560 | G5: =E5+F5 -> 468160 | H5: =ROUND(G5*НДС,0) -> 74906 | I5: =G5+H5 -> 543066 | J5: 2 | K5: =IF(J5=1,Мес_2026_новые,MAX(0,4-J5)) -> 2 | L5: =I5*K5 -> 1086132
A6: 3 | B6: Разработчик (ИИ, ГИС), платформа | C6: Руководителю цифрового развития | D6: Разработка и сопровождение ИИ- и ГИС-инструментов, цифровой платформы | E6: 1000000 | F6: =ROUND(E6*'Комиссия Antal'!$B$4,0) -> 100000 | G6: =E6+F6 -> 1100000 | H6: =ROUND(G6*НДС,0) -> 176000 | I6: =G6+H6 -> 1276000 | J6: 2 | K6: =IF(J6=1,Мес_2026_новые,MAX(0,4-J6)) -> 2 | L6: =I6*K6 -> 2552000
A7: 4 | B7: Режиссёр, видеограф-монтажёр | C7: Руководителю группы «Коммуникация и креатив» | D7: Съёмка и монтаж видео, ролики | E7: 1000000 | F7: =ROUND(E7*'Комиссия Antal'!$B$4,0) -> 100000 | G7: =E7+F7 -> 1100000 | H7: =ROUND(G7*НДС,0) -> 176000 | I7: =G7+H7 -> 1276000 | J7: 2 | K7: =IF(J7=1,Мес_2026_новые,MAX(0,4-J7)) -> 2 | L7: =I7*K7 -> 2552000
A8: 5 | B8: Копирайтер | C8: Руководителю группы «Коммуникация и креатив» | D8: Тексты для соцсетей, сайта, СМИ | E8: 700000 | F8: =ROUND(E8*'Комиссия Antal'!$B$4,0) -> 70000 | G8: =E8+F8 -> 770000 | H8: =ROUND(G8*НДС,0) -> 123200 | I8: =G8+H8 -> 893200 | J8: 2 | K8: =IF(J8=1,Мес_2026_новые,MAX(0,4-J8)) -> 2 | L8: =I8*K8 -> 1786400
A9: 6 | B9: Социолог (Нурканат А.) | C9: Руководителю департамента социологии | D9: Опросы и полевые работы, обработка данных | E9: 700000 | F9: =ROUND(E9*'Комиссия Antal'!$B$4,0) -> 70000 | G9: =E9+F9 -> 770000 | H9: =ROUND(G9*НДС,0) -> 123200 | I9: =G9+H9 -> 893200 | J9: 2 | K9: =IF(J9=1,Мес_2026_новые,MAX(0,4-J9)) -> 2 | L9: =I9*K9 -> 1786400
A10: 7 | B10: Менеджер по креаторам и креативным проектам | C10: Руководителю группы «Коммуникация и креатив» | D10: Работа с креаторами, креативные проекты | E10: 700000 | F10: =ROUND(E10*'Комиссия Antal'!$B$4,0) -> 70000 | G10: =E10+F10 -> 770000 | H10: =ROUND(G10*НДС,0) -> 123200 | I10: =G10+H10 -> 893200 | J10: 2 | K10: =IF(J10=1,Мес_2026_новые,MAX(0,4-J10)) -> 2 | L10: =I10*K10 -> 1786400
B11: ИТОГО аутсорс | E11: =SUM(E4:E10) -> 5393100 | F11: =SUM(F4:F10) -> 539310 | G11: =SUM(G4:G10) -> 5932410 | H11: =SUM(H4:H10) -> 949186 | I11: =SUM(I4:I10) -> 6881596 | L11: =SUM(L4:L10) -> 13763192
B12: Вознаграждение Antal – 10% от суммы «зарплата и налоги работодателя» (п. 6.1 договора), ставка берётся с листа «Комиссия Antal», ячейка B4. НДС 16% начисляется на стоимость вместе с вознаграждением по всем специалистам: решение 24.10.2026 – все оформляются через Antal Kazakhstan, ТОО на общеустановленном режиме и плательщик НДС.

Sheet Комиссия Antal
A1: Вознаграждение Antal Kazakhstan за аутстаффинг: сколько Фонд платит за посредничество
A2: Источник – КП «Аутстаффинг» для ЦАКФ и проект договора (п. 6.1): вознаграждение 10% не от оклада, а от «окончательной суммы» – фонда оплаты труда вместе с налогами работодателя; НДС начисляется сверху на всё, включая само вознаграждение. Ставки налогов берутся с листа «Параметры».
A4: Ставка вознаграждения Antal | B4: 0.1 | C4: п. 6.1 договора; фиксируется на срок контракта 3 года
A5: Эффективная ставка налогов работодателя | B5: =Ставка_ОПВР+Ставка_ООСМС+Ставка_СН*(1-Ставка_ОПВ-Ставка_ВОСМС) -> 0.1178 | C5: ОПВР + ООСМС + социальный налог от дохода за вычетом ОПВ и ВОСМС. Социальные отчисления не прибавляются: на них уменьшается социальный налог и при окладе выше 564 тыс. ₸ они гасятся полностью
A7: Оклад начисленный (гросс), ₸/мес | B7: Налоги работодателя, ₸ | C7: База вознаграждения, ₸ | D7: Вознаграждение Antal, ₸ | E7: НДС на вознаграждение, ₸ | F7: Вознаграждение с НДС, ₸ | G7: Без НДС, % от оклада
A8: 500000 | B8: =A8*$B$5 -> 58900 | C8: =A8+B8 -> 558900 | D8: =C8*$B$4 -> 55890 | E8: =D8*НДС -> 8942.4 | F8: =D8+E8 -> 64832.4 | G8: =D8/A8 -> 0.11178
A9: 700000 | B9: =A9*$B$5 -> 82460 | C9: =A9+B9 -> 782460 | D9: =C9*$B$4 -> 78246 | E9: =D9*НДС -> 12519.36 | F9: =D9+E9 -> 90765.36 | G9: =D9/A9 -> 0.11178
A10: 813286 | B10: =A10*$B$5 -> 95805.091 | C10: =A10+B10 -> 909091.09 | D10: =C10*$B$4 -> 90909.109 | E10: =D10*НДС -> 14545.457 | F10: =D10+E10 -> 105454.57 | G10: =D10/A10 -> 0.11178
A11: 1000000 | B11: =A11*$B$5 -> 117800 | C11: =A11+B11 -> 1117800 | D11: =C11*$B$4 -> 111780 | E11: =D11*НДС -> 17884.8 | F11: =D11+E11 -> 129664.8 | G11: =D11/A11 -> 0.11178
A13: Правило в одну строку
A14: Вознаграждение без НДС, % от оклада | B14: =$B$4*(1+$B$5) -> 0.11178 | C14: Реальные расходы Фонда: входной НДС берётся в зачёт
A15: Вознаграждение с НДС, % от оклада | B15: =$B$4*(1+$B$5)*(1+НДС) -> 0.1296648 | C15: Столько видно в счёте Antal
A17: Вознаграждение Antal по аутсорс-блоку бюджета (лист «Аутсорс», октябрь–декабрь 2026)
A18: Вознаграждение Antal по аутсорс-блоку бюджета (лист «Аутсорс», колонка «Вознаграждение Antal 10%»)
A19: Стоимость специалистов (зарплата и налоги), ₸/мес | B19: =Аутсорс!E11 -> 5393100
A20: Вознаграждение Antal, ₸/мес без НДС | B20: =Аутсорс!F11 -> 539310
A21: Вознаграждение Antal за квартал без НДС, ₸ | B21: =Аутсорс!F11*2 -> 1078620
A22: Вознаграждение Antal за квартал с НДС, ₸ | B22: =B21*(1+НДС) -> 1251199.2
A23: Аутсорс за период всего с вознаграждением и НДС, ₸ | B23: =Аутсорс!L11 -> 13763192
A25: Вознаграждение посчитано по каждому аутсорс-специалисту на листе «Аутсорс», колонка F. Подробный расчёт с рекрутингом – D:\Закупки\1 Процедуры закупок\9 Реестры и списки\Расчёт – аутстаффинг через Antal по тарифам КП (проект 2026-10-23).xlsx

Sheet Командировки
A1: Командировки по РК на октябрь–декабрь 2026 года, ₸
A2: Нормы поездок — на человека; стоимость поездки — лист «Параметры»; количество и старт — с листа «Штат».
A4: Роль | B4: Строка «Штат» | C4: Кол-во чел. | D4: Поездок по РК в год на чел. | E4: Выездов по макрорегиону в мес. на чел. | F4: Мес. 2026 (поездки – с ноября) | G4: Окт–дек 2026
A5: =Штат!C5 -> Главный исполнительный директор (ГИД) | C5: =Штат!G5 -> 1 | D5: 4 | E5: 0 | F5: =MIN(2,Штат!L5) -> 2 | G5: =C5*(D5/12*F5*Поездка_РК+E5*F5*Поездка_местн) -> 127300
A6: =Штат!C6 -> Советник ГИД по стратегии и науке | C6: =Штат!G6 -> 1 | D6: 6 | E6: 0 | F6: =MIN(2,Штат!L6) -> 2 | G6: =C6*(D6/12*F6*Поездка_РК+E6*F6*Поездка_местн) -> 190950
A7: =Штат!C8 -> Руководитель проектного офиса «Таза Қазақстан» | C7: =Штат!G8 -> 1 | D7: 10 | E7: 0 | F7: =MIN(2,Штат!L8) -> 2 | G7: =C7*(D7/12*F7*Поездка_РК+E7*F7*Поездка_местн) -> 318250
A8: Департамент социологических исследований и аналитики (3 чел.) | C8: =SUMIFS(Штат!$G$5:$G$36,Штат!$B$5:$B$36,"Департамент социологических*",Штат!$E$5:$E$36,"штат") -> 3 | D8: 3 | E8: 3 | F8: =MIN(2,IF(C8>0,SUMIFS(Штат!$L$5:$L$36,Штат!$B$5:$B$36,"Департамент социологических*",Штат!$E$5:$E$36,"штат")/C8,0)) -> 1.6666667 | G8: =C8*(D8/12*F8*Поездка_РК+E8*F8*Поездка_местн) -> 593437.5
A9: Департамент проектного управления и региональной координации (5 чел.) | C9: =SUMIFS(Штат!$G$5:$G$36,Штат!$B$5:$B$36,"Департамент проектного управления*",Штат!$E$5:$E$36,"штат") -> 5 | D9: 6 | E9: 0 | F9: =MIN(2,IF(C9>0,SUMIFS(Штат!$L$5:$L$36,Штат!$B$5:$B$36,"Департамент проектного управления*",Штат!$E$5:$E$36,"штат")/C9,0)) -> 2 | G9: =C9*(D9/12*F9*Поездка_РК+E9*F9*Поездка_местн) -> 954750
A10: Департамент цифрового развития (1 чел., разработчик — аутсорс) | C10: =SUM(Штат!G20:G21) -> 1 | D10: 1 | E10: 0 | F10: =MIN(2,Штат!L20) -> 2 | G10: =C10*(D10/12*F10*Поездка_РК+E10*F10*Поездка_местн) -> 31825
A11: Группа «Коммуникация и креатив» (5 чел.): съёмки и освещение мероприятий в регионах | C11: =SUM(Штат!G22:G29) -> 5 | D11: 4 | E11: 4 | F11: =MIN(2,Штат!L22) -> 2 | G11: =C11*(D11/12*F11*Поездка_РК+E11*F11*Поездка_местн) -> 1582500
A12: ИТОГО | G12: =SUM(G5:G11) -> 3799012.5

Sheet Оснащение и офис
A1: Оснащение, офис, цифровые инструменты и медиа на октябрь–декабрь 2026 года, ₸
A2: Тип: разово – в месяц старта; мес – ежемесячно с месяца старта; год – годовая сумма × 3/12.
A4: Раздел | B4: Статья | C4: Ед. | D4: Кол-во | E4: Цена, ₸ | F4: Тип | G4: Старт (1 – октябрь) | I4: Окт–дек 2026 | J4: Ноябрь 2026 | K4: Декабрь 2026 | L4: Январь 2027 | M4: Месяц оплаты разовых (11 / 12)
A5: Оснащение | B5: Ноутбук стандартный (Core i5 / Ryzen 5, 16 ГБ, SSD 512 ГБ) | C5: шт. | D5: 4 | E5: 450000 | F5: разово | G5: 1 | I5: =IF(F5="разово",IF(G5<=3,D5*E5,0),IF(F5="мес",D5*E5*MAX(0,4-G5),D5*E5*MAX(0,4-G5)/12)) -> 1800000 | J5: =IF($F5="разово",IF($M5=12,0,$I5),IF($F5="мес",$D5*$E5*(($G5<=1)+($G5<=2)),IF($F5="год",$D5*$E5/12*(($G5<=1)+($G5<=2)),$I5/2))) -> 1800000 | K5: =IF($F5="разово",IF($M5=12,$I5,0),IF($F5="мес",$D5*$E5*($G5<=3),IF($F5="год",$D5*$E5/12*($G5<=3),$I5/2))) -> 0 | L5: =IF($F5="разово",0,IF($F5="мес",$D5*$E5*($G5<=3),IF($F5="год",$D5*$E5/12*($G5<=3),$I5/2))) -> 0 | M5: 11
A6: Оснащение | B6: Ноутбук производительный | C6: шт. | D6: 1 | E6: 900000 | F6: разово | G6: 1 | I6: =IF(F6="разово",IF(G6<=3,D6*E6,0),IF(F6="мес",D6*E6*MAX(0,4-G6),D6*E6*MAX(0,4-G6)/12)) -> 900000 | J6: =IF($F6="разово",IF($M6=12,0,$I6),IF($F6="мес",$D6*$E6*(($G6<=1)+($G6<=2)),IF($F6="год",$D6*$E6/12*(($G6<=1)+($G6<=2)),$I6/2))) -> 900000 | K6: =IF($F6="разово",IF($M6=12,$I6,0),IF($F6="мес",$D6*$E6*($G6<=3),IF($F6="год",$D6*$E6/12*($G6<=3),$I6/2))) -> 0 | L6: =IF($F6="разово",0,IF($F6="мес",$D6*$E6*($G6<=3),IF($F6="год",$D6*$E6/12*($G6<=3),$I6/2))) -> 0 | M6: 11
A7: Оснащение | B7: Монитор 24" + клавиатура, мышь, гарнитура | C7: компл. | D7: 5 | E7: 100000 | F7: разово | G7: 1 | I7: =IF(F7="разово",IF(G7<=3,D7*E7,0),IF(F7="мес",D7*E7*MAX(0,4-G7),D7*E7*MAX(0,4-G7)/12)) -> 500000 | J7: =IF($F7="разово",IF($M7=12,0,$I7),IF($F7="мес",$D7*$E7*(($G7<=1)+($G7<=2)),IF($F7="год",$D7*$E7/12*(($G7<=1)+($G7<=2)),$I7/2))) -> 500000 | K7: =IF($F7="разово",IF($M7=12,$I7,0),IF($F7="мес",$D7*$E7*($G7<=3),IF($F7="год",$D7*$E7/12*($G7<=3),$I7/2))) -> 0 | L7: =IF($F7="разово",0,IF($F7="мес",$D7*$E7*($G7<=3),IF($F7="год",$D7*$E7/12*($G7<=3),$I7/2))) -> 0 | M7: 11
A8: Оснащение | B8: Стол рабочий с подкатной тумбой (ZETA Лофт, 140×70×77,7 см, ЛДСП, каркас металл, тумба на колёсах с 3 ящиками) | C8: шт. | D8: 20 | E8: =ROUND(80861/(1+НДС),0) -> 69708 | F8: разово | G8: 1 | I8: =IF(F8="разово",IF(G8<=3,D8*E8,0),IF(F8="мес",D8*E8*MAX(0,4-G8),D8*E8*MAX(0,4-G8)/12)) -> 1394160 | J8: =IF($F8="разово",IF($M8=12,0,$I8),IF($F8="мес",$D8*$E8*(($G8<=1)+($G8<=2)),IF($F8="год",$D8*$E8/12*(($G8<=1)+($G8<=2)),$I8/2))) -> 1394160 | K8: =IF($F8="разово",IF($M8=12,$I8,0),IF($F8="мес",$D8*$E8*($G8<=3),IF($F8="год",$D8*$E8/12*($G8<=3),$I8/2))) -> 0 | L8: =IF($F8="разово",0,IF($F8="мес",$D8*$E8*($G8<=3),IF($F8="год",$D8*$E8/12*($G8<=3),$I8/2))) -> 0 | M8: 11
A9: Оснащение | B9: Кресло рабочее (МИ-6 Z, спинка-сетка, подлокотники, крестовина с колёсами, регулировка высоты, нагрузка 120 кг) | C9: шт. | D9: 26 | E9: =ROUND(17110/(1+НДС),0) -> 14750 | F9: разово | G9: 1 | I9: =IF(F9="разово",IF(G9<=3,D9*E9,0),IF(F9="мес",D9*E9*MAX(0,4-G9),D9*E9*MAX(0,4-G9)/12)) -> 383500 | J9: =IF($F9="разово",IF($M9=12,0,$I9),IF($F9="мес",$D9*$E9*(($G9<=1)+($G9<=2)),IF($F9="год",$D9*$E9/12*(($G9<=1)+($G9<=2)),$I9/2))) -> 383500 | K9: =IF($F9="разово",IF($M9=12,$I9,0),IF($F9="мес",$D9*$E9*($G9<=3),IF($F9="год",$D9*$E9/12*($G9<=3),$I9/2))) -> 0 | L9: =IF($F9="разово",0,IF($F9="мес",$D9*$E9*($G9<=3),IF($F9="год",$D9*$E9/12*($G9<=3),$I9/2))) -> 0 | M9: 11
A10: Оснащение | B10: Кресло руководителя (ZETA Гермес, высокая спинка, механизм качания, подлокотники, нагрузка 120 кг) | C10: шт. | D10: 4 | E10: =ROUND(70900/(1+НДС),0) -> 61121 | F10: разово | G10: 1 | I10: =IF(F10="разово",IF(G10<=3,D10*E10,0),IF(F10="мес",D10*E10*MAX(0,4-G10),D10*E10*MAX(0,4-G10)/12)) -> 244484 | J10: =IF($F10="разово",IF($M10=12,0,$I10),IF($F10="мес",$D10*$E10*(($G10<=1)+($G10<=2)),IF($F10="год",$D10*$E10/12*(($G10<=1)+($G10<=2)),$I10/2))) -> 244484 | K10: =IF($F10="разово",IF($M10=12,$I10,0),IF($F10="мес",$D10*$E10*($G10<=3),IF($F10="год",$D10*$E10/12*($G10<=3),$I10/2))) -> 0 | L10: =IF($F10="разово",0,IF($F10="мес",$D10*$E10*($G10<=3),IF($F10="год",$D10*$E10/12*($G10<=3),$I10/2))) -> 0 | M10: 11
A11: Оснащение | B11: Кресло Главного исполнительного директора (ZETA мод. 2338, экокожа, высокая спинка, нагрузка 120 кг) | C11: шт. | D11: 1 | E11: =ROUND(114460/(1+НДС),0) -> 98672 | F11: разово | G11: 1 | I11: =IF(F11="разово",IF(G11<=3,D11*E11,0),IF(F11="мес",D11*E11*MAX(0,4-G11),D11*E11*MAX(0,4-G11)/12)) -> 98672 | J11: =IF($F11="разово",IF($M11=12,0,$I11),IF($F11="мес",$D11*$E11*(($G11<=1)+($G11<=2)),IF($F11="год",$D11*$E11/12*(($G11<=1)+($G11<=2)),$I11/2))) -> 98672 | K11: =IF($F11="разово",IF($M11=12,$I11,0),IF($F11="мес",$D11*$E11*($G11<=3),IF($F11="год",$D11*$E11/12*($G11<=3),$I11/2))) -> 0 | L11: =IF($F11="разово",0,IF($F11="мес",$D11*$E11*($G11<=3),IF($F11="год",$D11*$E11/12*($G11<=3),$I11/2))) -> 0 | M11: 11
A12: Оснащение | B12: Стол руководителя (ZETA Тейлор, 140×70×75 см, светло-серый) | C12: шт. | D12: 0 | E12: =ROUND(67576/(1+НДС),0) -> 58255 | F12: разово | G12: 1 | I12: =IF(F12="разово",IF(G12<=3,D12*E12,0),IF(F12="мес",D12*E12*MAX(0,4-G12),D12*E12*MAX(0,4-G12)/12)) -> 0 | J12: =IF($F12="разово",IF($M12=12,0,$I12),IF($F12="мес",$D12*$E12*(($G12<=1)+($G12<=2)),IF($F12="год",$D12*$E12/12*(($G12<=1)+($G12<=2)),$I12/2))) -> 0 | K12: =IF($F12="разово",IF($M12=12,$I12,0),IF($F12="мес",$D12*$E12*($G12<=3),IF($F12="год",$D12*$E12/12*($G12<=3),$I12/2))) -> 0 | L12: =IF($F12="разово",0,IF($F12="мес",$D12*$E12*($G12<=3),IF($F12="год",$D12*$E12/12*($G12<=3),$I12/2))) -> 0 | M12: 11
A13: Оснащение | B13: Шкаф для документов финансовому директору, полностью закрытый, с замком (ZETA ШММ-1, металл, 42,5×37×176 см, 4 полки) | C13: шт. | D13: 1 | E13: =ROUND(45900/(1+НДС),0) -> 39569 | F13: разово | G13: 1 | I13: =IF(F13="разово",IF(G13<=3,D13*E13,0),IF(F13="мес",D13*E13*MAX(0,4-G13),D13*E13*MAX(0,4-G13)/12)) -> 39569 | J13: =IF($F13="разово",IF($M13=12,0,$I13),IF($F13="мес",$D13*$E13*(($G13<=1)+($G13<=2)),IF($F13="год",$D13*$E13/12*(($G13<=1)+($G13<=2)),$I13/2))) -> 39569 | K13: =IF($F13="разово",IF($M13=12,$I13,0),IF($F13="мес",$D13*$E13*($G13<=3),IF($F13="год",$D13*$E13/12*($G13<=3),$I13/2))) -> 0 | L13: =IF($F13="разово",0,IF($F13="мес",$D13*$E13*($G13<=3),IF($F13="год",$D13*$E13/12*($G13<=3),$I13/2))) -> 0 | M13: 11
A14: Оснащение | B14: Тумба офисная подкатная в кабинет руководителя (ZETA OZ9134000000ST, 44×61×40 см, на колёсиках, ящик и дверца) | C14: шт. | D14: 0 | E14: =ROUND(23645/(1+НДС),0) -> 20384 | F14: разово | G14: 1 | I14: =IF(F14="разово",IF(G14<=3,D14*E14,0),IF(F14="мес",D14*E14*MAX(0,4-G14),D14*E14*MAX(0,4-G14)/12)) -> 0 | J14: =IF($F14="разово",IF($M14=12,0,$I14),IF($F14="мес",$D14*$E14*(($G14<=1)+($G14<=2)),IF($F14="год",$D14*$E14/12*(($G14<=1)+($G14<=2)),$I14/2))) -> 0 | K14: =IF($F14="разово",IF($M14=12,$I14,0),IF($F14="мес",$D14*$E14*($G14<=3),IF($F14="год",$D14*$E14/12*($G14<=3),$I14/2))) -> 0 | L14: =IF($F14="разово",0,IF($F14="мес",$D14*$E14*($G14<=3),IF($F14="год",$D14*$E14/12*($G14<=3),$I14/2))) -> 0 | M14: 11
A15: Оснащение | B15: Шкаф-гардероб офисный в кабинет руководителя (со штангой и полкой, высота от 190 см) | C15: шт. | D15: 0 | E15: =ROUND(55451/(1+НДС),0) -> 47803 | F15: разово | G15: 1 | I15: =IF(F15="разово",IF(G15<=3,D15*E15,0),IF(F15="мес",D15*E15*MAX(0,4-G15),D15*E15*MAX(0,4-G15)/12)) -> 0 | J15: =IF($F15="разово",IF($M15=12,0,$I15),IF($F15="мес",$D15*$E15*(($G15<=1)+($G15<=2)),IF($F15="год",$D15*$E15/12*(($G15<=1)+($G15<=2)),$I15/2))) -> 0 | K15: =IF($F15="разово",IF($M15=12,$I15,0),IF($F15="мес",$D15*$E15*($G15<=3),IF($F15="год",$D15*$E15/12*($G15<=3),$I15/2))) -> 0 | L15: =IF($F15="разово",0,IF($F15="мес",$D15*$E15*($G15<=3),IF($F15="год",$D15*$E15/12*($G15<=3),$I15/2))) -> 0 | M15: 11
A16: Оснащение | B16: Вешалка-стойка напольная на крестовине, 7 крючков (ZETA Кактус, металл, 50×50×175 см) | C16: шт. | D16: 5 | E16: =ROUND(8950/(1+НДС),0) -> 7716 | F16: разово | G16: 1 | I16: =IF(F16="разово",IF(G16<=3,D16*E16,0),IF(F16="мес",D16*E16*MAX(0,4-G16),D16*E16*MAX(0,4-G16)/12)) -> 38580 | J16: =IF($F16="разово",IF($M16=12,0,$I16),IF($F16="мес",$D16*$E16*(($G16<=1)+($G16<=2)),IF($F16="год",$D16*$E16/12*(($G16<=1)+($G16<=2)),$I16/2))) -> 38580 | K16: =IF($F16="разово",IF($M16=12,$I16,0),IF($F16="мес",$D16*$E16*($G16<=3),IF($F16="год",$D16*$E16/12*($G16<=3),$I16/2))) -> 0 | L16: =IF($F16="разово",0,IF($F16="мес",$D16*$E16*($G16<=3),IF($F16="год",$D16*$E16/12*($G16<=3),$I16/2))) -> 0 | M16: 11
A17: Оснащение | B17: Комплект мебели кабинетов ГИД и руководителя проектного офиса (ILMER Рук: стол овальный 180×80, приставка 140×65, тумба 120×40, шкаф и стеллаж 210×180 – 6 предметов) | C17: компл. | D17: 2 | E17: =ROUND(249999/(1+НДС),0) -> 215516 | F17: разово | G17: 1 | I17: =IF(F17="разово",IF(G17<=3,D17*E17,0),IF(F17="мес",D17*E17*MAX(0,4-G17),D17*E17*MAX(0,4-G17)/12)) -> 431032 | J17: =IF($F17="разово",IF($M17=12,0,$I17),IF($F17="мес",$D17*$E17*(($G17<=1)+($G17<=2)),IF($F17="год",$D17*$E17/12*(($G17<=1)+($G17<=2)),$I17/2))) -> 431032 | K17: =IF($F17="разово",IF($M17=12,$I17,0),IF($F17="мес",$D17*$E17*($G17<=3),IF($F17="год",$D17*$E17/12*($G17<=3),$I17/2))) -> 0 | L17: =IF($F17="разово",0,IF($F17="мес",$D17*$E17*($G17<=3),IF($F17="год",$D17*$E17/12*($G17<=3),$I17/2))) -> 0 | M17: 11
A18: Оснащение | B18: Комплект мебели кабинетов заместителя ГИД и финансового директора (АТЛАНТИК К103, коричневый: шкаф плательный 800×400×1950, шкаф для документов 800×400×1950, стол 1100×600×750, стол с полкой для клавиатуры 800×600×750, приставка угловая 600×600 – 5 предметов) | C18: компл. | D18: 2 | E18: =ROUND(265000/(1+НДС),0) -> 228448 | F18: разово | G18: 1 | I18: =IF(F18="разово",IF(G18<=3,D18*E18,0),IF(F18="мес",D18*E18*MAX(0,4-G18),D18*E18*MAX(0,4-G18)/12)) -> 456896 | J18: =IF($F18="разово",IF($M18=12,0,$I18),IF($F18="мес",$D18*$E18*(($G18<=1)+($G18<=2)),IF($F18="год",$D18*$E18/12*(($G18<=1)+($G18<=2)),$I18/2))) -> 456896 | K18: =IF($F18="разово",IF($M18=12,$I18,0),IF($F18="мес",$D18*$E18*($G18<=3),IF($F18="год",$D18*$E18/12*($G18<=3),$I18/2))) -> 0 | L18: =IF($F18="разово",0,IF($F18="мес",$D18*$E18*($G18<=3),IF($F18="год",$D18*$E18/12*($G18<=3),$I18/2))) -> 0 | M18: 11
A19: Оснащение | B19: Стул представительский (ZETA Shugyla, 87×55×57 см, металл, обивка велюр, бежевый) | C19: шт. | D19: 3 | E19: =ROUND(26905/(1+НДС),0) -> 23194 | F19: разово | G19: 1 | I19: =IF(F19="разово",IF(G19<=3,D19*E19,0),IF(F19="мес",D19*E19*MAX(0,4-G19),D19*E19*MAX(0,4-G19)/12)) -> 69582 | J19: =IF($F19="разово",IF($M19=12,0,$I19),IF($F19="мес",$D19*$E19*(($G19<=1)+($G19<=2)),IF($F19="год",$D19*$E19/12*(($G19<=1)+($G19<=2)),$I19/2))) -> 69582 | K19: =IF($F19="разово",IF($M19=12,$I19,0),IF($F19="мес",$D19*$E19*($G19<=3),IF($F19="год",$D19*$E19/12*($G19<=3),$I19/2))) -> 0 | L19: =IF($F19="разово",0,IF($F19="мес",$D19*$E19*($G19<=3),IF($F19="год",$D19*$E19/12*($G19<=3),$I19/2))) -> 0 | M19: 11
A20: Оснащение | B20: Кухонный гарнитур ZETA Денвер, 200×215×60 см, ЛДСП, серый / бежевый | C20: компл. | D20: 1 | E20: =ROUND(118860/(1+НДС),0) -> 102466 | F20: разово | G20: 1 | I20: =IF(F20="разово",IF(G20<=3,D20*E20,0),IF(F20="мес",D20*E20*MAX(0,4-G20),D20*E20*MAX(0,4-G20)/12)) -> 102466 | J20: =IF($F20="разово",IF($M20=12,0,$I20),IF($F20="мес",$D20*$E20*(($G20<=1)+($G20<=2)),IF($F20="год",$D20*$E20/12*(($G20<=1)+($G20<=2)),$I20/2))) -> 102466 | K20: =IF($F20="разово",IF($M20=12,$I20,0),IF($F20="мес",$D20*$E20*($G20<=3),IF($F20="год",$D20*$E20/12*($G20<=3),$I20/2))) -> 0 | L20: =IF($F20="разово",0,IF($F20="мес",$D20*$E20*($G20<=3),IF($F20="год",$D20*$E20/12*($G20<=3),$I20/2))) -> 0 | M20: 11
A21: Оснащение | B21: Мойка врезная HALI со смесителем, 60×45×22 см, нерж. сталь 3 мм, графит | C21: компл. | D21: 1 | E21: =ROUND(36990/(1+НДС),0) -> 31888 | F21: разово | G21: 1 | I21: =IF(F21="разово",IF(G21<=3,D21*E21,0),IF(F21="мес",D21*E21*MAX(0,4-G21),D21*E21*MAX(0,4-G21)/12)) -> 31888 | J21: =IF($F21="разово",IF($M21=12,0,$I21),IF($F21="мес",$D21*$E21*(($G21<=1)+($G21<=2)),IF($F21="год",$D21*$E21/12*(($G21<=1)+($G21<=2)),$I21/2))) -> 31888 | K21: =IF($F21="разово",IF($M21=12,$I21,0),IF($F21="мес",$D21*$E21*($G21<=3),IF($F21="год",$D21*$E21/12*($G21<=3),$I21/2))) -> 0 | L21: =IF($F21="разово",0,IF($F21="мес",$D21*$E21*($G21<=3),IF($F21="год",$D21*$E21/12*($G21<=3),$I21/2))) -> 0 | M21: 11
A22: Оснащение | B22: Переговорная: стол + 12 стульев | C22: компл. | D22: 0 | E22: 800000 | F22: разово | G22: 1 | I22: =IF(F22="разово",IF(G22<=3,D22*E22,0),IF(F22="мес",D22*E22*MAX(0,4-G22),D22*E22*MAX(0,4-G22)/12)) -> 0 | J22: =IF($F22="разово",IF($M22=12,0,$I22),IF($F22="мес",$D22*$E22*(($G22<=1)+($G22<=2)),IF($F22="год",$D22*$E22/12*(($G22<=1)+($G22<=2)),$I22/2))) -> 0 | K22: =IF($F22="разово",IF($M22=12,$I22,0),IF($F22="мес",$D22*$E22*($G22<=3),IF($F22="год",$D22*$E22/12*($G22<=3),$I22/2))) -> 0 | L22: =IF($F22="разово",0,IF($F22="мес",$D22*$E22*($G22<=3),IF($F22="год",$D22*$E22/12*($G22<=3),$I22/2))) -> 0 | M22: 11
A23: Оснащение | B23: Стойка ресепшн | C23: компл. | D23: 0 | E23: 250000 | F23: разово | G23: 1 | I23: =IF(F23="разово",IF(G23<=3,D23*E23,0),IF(F23="мес",D23*E23*MAX(0,4-G23),D23*E23*MAX(0,4-G23)/12)) -> 0 | J23: =IF($F23="разово",IF($M23=12,0,$I23),IF($F23="мес",$D23*$E23*(($G23<=1)+($G23<=2)),IF($F23="год",$D23*$E23/12*(($G23<=1)+($G23<=2)),$I23/2))) -> 0 | K23: =IF($F23="разово",IF($M23=12,$I23,0),IF($F23="мес",$D23*$E23*($G23<=3),IF($F23="год",$D23*$E23/12*($G23<=3),$I23/2))) -> 0 | L23: =IF($F23="разово",0,IF($F23="мес",$D23*$E23*($G23<=3),IF($F23="год",$D23*$E23/12*($G23<=3),$I23/2))) -> 0 | M23: 11
A24: Оснащение | B24: Шкафы для документов | C24: компл. | D24: 0 | E24: 100000 | F24: разово | G24: 1 | I24: =IF(F24="разово",IF(G24<=3,D24*E24,0),IF(F24="мес",D24*E24*MAX(0,4-G24),D24*E24*MAX(0,4-G24)/12)) -> 0 | J24: =IF($F24="разово",IF($M24=12,0,$I24),IF($F24="мес",$D24*$E24*(($G24<=1)+($G24<=2)),IF($F24="год",$D24*$E24/12*(($G24<=1)+($G24<=2)),$I24/2))) -> 0 | K24: =IF($F24="разово",IF($M24=12,$I24,0),IF($F24="мес",$D24*$E24*($G24<=3),IF($F24="год",$D24*$E24/12*($G24<=3),$I24/2))) -> 0 | L24: =IF($F24="разово",0,IF($F24="мес",$D24*$E24*($G24<=3),IF($F24="год",$D24*$E24/12*($G24<=3),$I24/2))) -> 0 | M24: 11
A25: Оснащение | B25: Стеллажи для складов и архивов (склад техники, архив документов, архив основного блока) | C25: шт. | D25: 0 | E25: 60000 | F25: разово | G25: 1 | I25: =IF(F25="разово",IF(G25<=3,D25*E25,0),IF(F25="мес",D25*E25*MAX(0,4-G25),D25*E25*MAX(0,4-G25)/12)) -> 0 | J25: =IF($F25="разово",IF($M25=12,0,$I25),IF($F25="мес",$D25*$E25*(($G25<=1)+($G25<=2)),IF($F25="год",$D25*$E25/12*(($G25<=1)+($G25<=2)),$I25/2))) -> 0 | K25: =IF($F25="разово",IF($M25=12,$I25,0),IF($F25="мес",$D25*$E25*($G25<=3),IF($F25="год",$D25*$E25/12*($G25<=3),$I25/2))) -> 0 | L25: =IF($F25="разово",0,IF($F25="мес",$D25*$E25*($G25<=3),IF($F25="год",$D25*$E25/12*($G25<=3),$I25/2))) -> 0 | M25: 11
A26: Оснащение | B26: Сборка, доставка и подъём мебели | C26: компл. | D26: 1 | E26: =SUMPRODUCT(D8:D25,E8:E25)*Сборка_мебели_проц -> 329082.9 | F26: разово | G26: 1 | I26: =IF(F26="разово",IF(G26<=3,D26*E26,0),IF(F26="мес",D26*E26*MAX(0,4-G26),D26*E26*MAX(0,4-G26)/12)) -> 329082.9 | J26: =IF($F26="разово",IF($M26=12,0,$I26),IF($F26="мес",$D26*$E26*(($G26<=1)+($G26<=2)),IF($F26="год",$D26*$E26/12*(($G26<=1)+($G26<=2)),$I26/2))) -> 329082.9 | K26: =IF($F26="разово",IF($M26=12,$I26,0),IF($F26="мес",$D26*$E26*($G26<=3),IF($F26="год",$D26*$E26/12*($G26<=3),$I26/2))) -> 0 | L26: =IF($F26="разово",0,IF($F26="мес",$D26*$E26*($G26<=3),IF($F26="год",$D26*$E26/12*($G26<=3),$I26/2))) -> 0 | M26: 11
A27: Оснащение | B27: Врезка мойки, подключение воды и канализации на кухонной зоне | C27: компл. | D27: 1 | E27: =ROUND(25000/(1+НДС),0) -> 21552 | F27: разово | G27: 1 | I27: =IF(F27="разово",IF(G27<=3,D27*E27,0),IF(F27="мес",D27*E27*MAX(0,4-G27),D27*E27*MAX(0,4-G27)/12)) -> 21552 | J27: =IF($F27="разово",IF($M27=12,0,$I27),IF($F27="мес",$D27*$E27*(($G27<=1)+($G27<=2)),IF($F27="год",$D27*$E27/12*(($G27<=1)+($G27<=2)),$I27/2))) -> 21552 | K27: =IF($F27="разово",IF($M27=12,$I27,0),IF($F27="мес",$D27*$E27*($G27<=3),IF($F27="год",$D27*$E27/12*($G27<=3),$I27/2))) -> 0 | L27: =IF($F27="разово",0,IF($F27="мес",$D27*$E27*($G27<=3),IF($F27="год",$D27*$E27/12*($G27<=3),$I27/2))) -> 0 | M27: 11
A28: Оснащение | B28: МФУ цветное А3 (класс Kyocera TASKalfa 2554ci) с Wi-Fi, тумбой, доставкой и установкой | C28: шт. | D28: 1 | E28: 2500000 | F28: разово | G28: 1 | I28: =IF(F28="разово",IF(G28<=3,D28*E28,0),IF(F28="мес",D28*E28*MAX(0,4-G28),D28*E28*MAX(0,4-G28)/12)) -> 2500000 | J28: =IF($F28="разово",IF($M28=12,0,$I28),IF($F28="мес",$D28*$E28*(($G28<=1)+($G28<=2)),IF($F28="год",$D28*$E28/12*(($G28<=1)+($G28<=2)),$I28/2))) -> 2500000 | K28: =IF($F28="разово",IF($M28=12,$I28,0),IF($F28="мес",$D28*$E28*($G28<=3),IF($F28="год",$D28*$E28/12*($G28<=3),$I28/2))) -> 0 | L28: =IF($F28="разово",0,IF($F28="мес",$D28*$E28*($G28<=3),IF($F28="год",$D28*$E28/12*($G28<=3),$I28/2))) -> 0 | M28: 11
A29: Оснащение | B29: Стартовый комплект тонеров CMYK для МФУ А3 | C29: компл. | D29: 1 | E29: 300000 | F29: разово | G29: 1 | I29: =IF(F29="разово",IF(G29<=3,D29*E29,0),IF(F29="мес",D29*E29*MAX(0,4-G29),D29*E29*MAX(0,4-G29)/12)) -> 300000 | J29: =IF($F29="разово",IF($M29=12,0,$I29),IF($F29="мес",$D29*$E29*(($G29<=1)+($G29<=2)),IF($F29="год",$D29*$E29/12*(($G29<=1)+($G29<=2)),$I29/2))) -> 300000 | K29: =IF($F29="разово",IF($M29=12,$I29,0),IF($F29="мес",$D29*$E29*($G29<=3),IF($F29="год",$D29*$E29/12*($G29<=3),$I29/2))) -> 0 | L29: =IF($F29="разово",0,IF($F29="мес",$D29*$E29*($G29<=3),IF($F29="год",$D29*$E29/12*($G29<=3),$I29/2))) -> 0 | M29: 11
A30: Оснащение | B30: МФУ А4 чёрно-белое с Wi-Fi, дуплексом и автоподатчиком (класс HP LaserJet Pro MFP 4103fdw / Kyocera ECOSYS MA4000fx) | C30: шт. | D30: 2 | E30: 280000 | F30: разово | G30: 1 | I30: =IF(F30="разово",IF(G30<=3,D30*E30,0),IF(F30="мес",D30*E30*MAX(0,4-G30),D30*E30*MAX(0,4-G30)/12)) -> 560000 | J30: =IF($F30="разово",IF($M30=12,0,$I30),IF($F30="мес",$D30*$E30*(($G30<=1)+($G30<=2)),IF($F30="год",$D30*$E30/12*(($G30<=1)+($G30<=2)),$I30/2))) -> 560000 | K30: =IF($F30="разово",IF($M30=12,$I30,0),IF($F30="мес",$D30*$E30*($G30<=3),IF($F30="год",$D30*$E30/12*($G30<=3),$I30/2))) -> 0 | L30: =IF($F30="разово",0,IF($F30="мес",$D30*$E30*($G30<=3),IF($F30="год",$D30*$E30/12*($G30<=3),$I30/2))) -> 0 | M30: 11
A31: Оснащение | B31: Резервные картриджи для МФУ А4 (по 2 на аппарат) | C31: шт. | D31: 4 | E31: 55000 | F31: разово | G31: 1 | I31: =IF(F31="разово",IF(G31<=3,D31*E31,0),IF(F31="мес",D31*E31*MAX(0,4-G31),D31*E31*MAX(0,4-G31)/12)) -> 220000 | J31: =IF($F31="разово",IF($M31=12,0,$I31),IF($F31="мес",$D31*$E31*(($G31<=1)+($G31<=2)),IF($F31="год",$D31*$E31/12*(($G31<=1)+($G31<=2)),$I31/2))) -> 0 | K31: =IF($F31="разово",IF($M31=12,$I31,0),IF($F31="мес",$D31*$E31*($G31<=3),IF($F31="год",$D31*$E31/12*($G31<=3),$I31/2))) -> 220000 | L31: =IF($F31="разово",0,IF($F31="мес",$D31*$E31*($G31<=3),IF($F31="год",$D31*$E31/12*($G31<=3),$I31/2))) -> 0 | M31: 12
A32: Оснащение | B32: Резервный комплект тонеров CMYK для МФУ А3 | C32: компл. | D32: 1 | E32: 300000 | F32: разово | G32: 1 | I32: =IF(F32="разово",IF(G32<=3,D32*E32,0),IF(F32="мес",D32*E32*MAX(0,4-G32),D32*E32*MAX(0,4-G32)/12)) -> 300000 | J32: =IF($F32="разово",IF($M32=12,0,$I32),IF($F32="мес",$D32*$E32*(($G32<=1)+($G32<=2)),IF($F32="год",$D32*$E32/12*(($G32<=1)+($G32<=2)),$I32/2))) -> 0 | K32: =IF($F32="разово",IF($M32=12,$I32,0),IF($F32="мес",$D32*$E32*($G32<=3),IF($F32="год",$D32*$E32/12*($G32<=3),$I32/2))) -> 300000 | L32: =IF($F32="разово",0,IF($F32="мес",$D32*$E32*($G32<=3),IF($F32="год",$D32*$E32/12*($G32<=3),$I32/2))) -> 0 | M32: 12
A33: Оснащение | B33: Ламинатор Deli ET104, А3, 300 мм/мин | C33: шт. | E33: =ROUND(42340/(1+НДС),0) -> 36500 | F33: разово | G33: 1 | I33: =IF(F33="разово",IF(G33<=3,D33*E33,0),IF(F33="мес",D33*E33*MAX(0,4-G33),D33*E33*MAX(0,4-G33)/12)) -> 0 | J33: =IF($F33="разово",IF($M33=12,0,$I33),IF($F33="мес",$D33*$E33*(($G33<=1)+($G33<=2)),IF($F33="год",$D33*$E33/12*(($G33<=1)+($G33<=2)),$I33/2))) -> 0 | K33: =IF($F33="разово",IF($M33=12,$I33,0),IF($F33="мес",$D33*$E33*($G33<=3),IF($F33="год",$D33*$E33/12*($G33<=3),$I33/2))) -> 0 | L33: =IF($F33="разово",0,IF($F33="мес",$D33*$E33*($G33<=3),IF($F33="год",$D33*$E33/12*($G33<=3),$I33/2))) -> 0 | M33: 11
A34: Оснащение | B34: Плёнка для ламинирования А4, 100 мкм, 100 шт. в упаковке (OfficeSpace) | C34: уп. | E34: =ROUND(6000/(1+НДС),0) -> 5172 | F34: разово | G34: 1 | I34: =IF(F34="разово",IF(G34<=3,D34*E34,0),IF(F34="мес",D34*E34*MAX(0,4-G34),D34*E34*MAX(0,4-G34)/12)) -> 0 | J34: =IF($F34="разово",IF($M34=12,0,$I34),IF($F34="мес",$D34*$E34*(($G34<=1)+($G34<=2)),IF($F34="год",$D34*$E34/12*(($G34<=1)+($G34<=2)),$I34/2))) -> 0 | K34: =IF($F34="разово",IF($M34=12,$I34,0),IF($F34="мес",$D34*$E34*($G34<=3),IF($F34="год",$D34*$E34/12*($G34<=3),$I34/2))) -> 0 | L34: =IF($F34="разово",0,IF($F34="мес",$D34*$E34*($G34<=3),IF($F34="год",$D34*$E34/12*($G34<=3),$I34/2))) -> 0 | M34: 11
A35: Оснащение | B35: Переплётная машина Deli 3873 для пластиковой пружины (перфорирует до 18 л., сшивает до 425 л.) | C35: шт. | E35: =ROUND(114327/(1+НДС),0) -> 98558 | F35: разово | G35: 1 | I35: =IF(F35="разово",IF(G35<=3,D35*E35,0),IF(F35="мес",D35*E35*MAX(0,4-G35),D35*E35*MAX(0,4-G35)/12)) -> 0 | J35: =IF($F35="разово",IF($M35=12,0,$I35),IF($F35="мес",$D35*$E35*(($G35<=1)+($G35<=2)),IF($F35="год",$D35*$E35/12*(($G35<=1)+($G35<=2)),$I35/2))) -> 0 | K35: =IF($F35="разово",IF($M35=12,$I35,0),IF($F35="мес",$D35*$E35*($G35<=3),IF($F35="год",$D35*$E35/12*($G35<=3),$I35/2))) -> 0 | L35: =IF($F35="разово",0,IF($F35="мес",$D35*$E35*($G35<=3),IF($F35="год",$D35*$E35/12*($G35<=3),$I35/2))) -> 0 | M35: 11
A36: Оснащение | B36: Расходники для переплёта: обложки А4 картонные и пластиковые, пружины 6, 10, 14 и 51 мм (по 100 шт.) | C36: компл. | E36: =ROUND((100*55+100*68+100*26+100*37+100*57+100*244)/(1+НДС),0) -> 41983 | F36: разово | G36: 1 | I36: =IF(F36="разово",IF(G36<=3,D36*E36,0),IF(F36="мес",D36*E36*MAX(0,4-G36),D36*E36*MAX(0,4-G36)/12)) -> 0 | J36: =IF($F36="разово",IF($M36=12,0,$I36),IF($F36="мес",$D36*$E36*(($G36<=1)+($G36<=2)),IF($F36="год",$D36*$E36/12*(($G36<=1)+($G36<=2)),$I36/2))) -> 0 | K36: =IF($F36="разово",IF($M36=12,$I36,0),IF($F36="мес",$D36*$E36*($G36<=3),IF($F36="год",$D36*$E36/12*($G36<=3),$I36/2))) -> 0 | L36: =IF($F36="разово",0,IF($F36="мес",$D36*$E36*($G36<=3),IF($F36="год",$D36*$E36/12*($G36<=3),$I36/2))) -> 0 | M36: 11
A37: Оснащение | B37: Сетевые фильтры на рабочие места: 5 розеток, 3 м, с заземлением (Defender ES) | C37: шт. | D37: 21 | E37: =ROUND(4118/(1+НДС),0) -> 3550 | F37: разово | G37: 1 | I37: =IF(F37="разово",IF(G37<=3,D37*E37,0),IF(F37="мес",D37*E37*MAX(0,4-G37),D37*E37*MAX(0,4-G37)/12)) -> 74550 | J37: =IF($F37="разово",IF($M37=12,0,$I37),IF($F37="мес",$D37*$E37*(($G37<=1)+($G37<=2)),IF($F37="год",$D37*$E37/12*(($G37<=1)+($G37<=2)),$I37/2))) -> 74550 | K37: =IF($F37="разово",IF($M37=12,$I37,0),IF($F37="мес",$D37*$E37*($G37<=3),IF($F37="год",$D37*$E37/12*($G37<=3),$I37/2))) -> 0 | L37: =IF($F37="разово",0,IF($F37="мес",$D37*$E37*($G37<=3),IF($F37="год",$D37*$E37/12*($G37<=3),$I37/2))) -> 0 | M37: 11
A38: Оснащение | B38: Сетевые фильтры на общие зоны: 6 розеток, 5 м (Defender DFS 155) | C38: шт. | D38: 3 | E38: =ROUND(6101/(1+НДС),0) -> 5259 | F38: разово | G38: 1 | I38: =IF(F38="разово",IF(G38<=3,D38*E38,0),IF(F38="мес",D38*E38*MAX(0,4-G38),D38*E38*MAX(0,4-G38)/12)) -> 15777 | J38: =IF($F38="разово",IF($M38=12,0,$I38),IF($F38="мес",$D38*$E38*(($G38<=1)+($G38<=2)),IF($F38="год",$D38*$E38/12*(($G38<=1)+($G38<=2)),$I38/2))) -> 15777 | K38: =IF($F38="разово",IF($M38=12,$I38,0),IF($F38="мес",$D38*$E38*($G38<=3),IF($F38="год",$D38*$E38/12*($G38<=3),$I38/2))) -> 0 | L38: =IF($F38="разово",0,IF($F38="мес",$D38*$E38*($G38<=3),IF($F38="год",$D38*$E38/12*($G38<=3),$I38/2))) -> 0 | M38: 11
A39: Оснащение | B39: Удлинители-магистрали 10 м, 3 розетки, с заземлением, ПВС 3×1 мм², 16 А (ЭРА U-3e-10m-3x1) | C39: шт. | D39: 4 | E39: =ROUND(7235/(1+НДС),0) -> 6237 | F39: разово | G39: 1 | I39: =IF(F39="разово",IF(G39<=3,D39*E39,0),IF(F39="мес",D39*E39*MAX(0,4-G39),D39*E39*MAX(0,4-G39)/12)) -> 24948 | J39: =IF($F39="разово",IF($M39=12,0,$I39),IF($F39="мес",$D39*$E39*(($G39<=1)+($G39<=2)),IF($F39="год",$D39*$E39/12*(($G39<=1)+($G39<=2)),$I39/2))) -> 24948 | K39: =IF($F39="разово",IF($M39=12,$I39,0),IF($F39="мес",$D39*$E39*($G39<=3),IF($F39="год",$D39*$E39/12*($G39<=3),$I39/2))) -> 0 | L39: =IF($F39="разово",0,IF($F39="мес",$D39*$E39*($G39<=3),IF($F39="год",$D39*$E39/12*($G39<=3),$I39/2))) -> 0 | M39: 11
A40: Оснащение | B40: Кабель-канал напольный ПВХ 70×16 мм, секция 2 м (IEK) | C40: шт. | D40: 10 | E40: =ROUND(9039/(1+НДС),0) -> 7792 | F40: разово | G40: 1 | I40: =IF(F40="разово",IF(G40<=3,D40*E40,0),IF(F40="мес",D40*E40*MAX(0,4-G40),D40*E40*MAX(0,4-G40)/12)) -> 77920 | J40: =IF($F40="разово",IF($M40=12,0,$I40),IF($F40="мес",$D40*$E40*(($G40<=1)+($G40<=2)),IF($F40="год",$D40*$E40/12*(($G40<=1)+($G40<=2)),$I40/2))) -> 77920 | K40: =IF($F40="разово",IF($M40=12,$I40,0),IF($F40="мес",$D40*$E40*($G40<=3),IF($F40="год",$D40*$E40/12*($G40<=3),$I40/2))) -> 0 | L40: =IF($F40="разово",0,IF($F40="мес",$D40*$E40*($G40<=3),IF($F40="год",$D40*$E40/12*($G40<=3),$I40/2))) -> 0 | M40: 11
A41: Оснащение | B41: Источник бесперебойного питания 1200 ВА / 650 Вт, линейно-интерактивный (APC Back-UPS BX1200MI-GR) | C41: шт. | D41: 10 | E41: =ROUND(89302/(1+НДС),0) -> 76984 | F41: разово | G41: 1 | I41: =IF(F41="разово",IF(G41<=3,D41*E41,0),IF(F41="мес",D41*E41*MAX(0,4-G41),D41*E41*MAX(0,4-G41)/12)) -> 769840 | J41: =IF($F41="разово",IF($M41=12,0,$I41),IF($F41="мес",$D41*$E41*(($G41<=1)+($G41<=2)),IF($F41="год",$D41*$E41/12*(($G41<=1)+($G41<=2)),$I41/2))) -> 769840 | K41: =IF($F41="разово",IF($M41=12,$I41,0),IF($F41="мес",$D41*$E41*($G41<=3),IF($F41="год",$D41*$E41/12*($G41<=3),$I41/2))) -> 0 | L41: =IF($F41="разово",0,IF($F41="мес",$D41*$E41*($G41<=3),IF($F41="год",$D41*$E41/12*($G41<=3),$I41/2))) -> 0 | M41: 11
A42: Оснащение | B42: Wi-Fi роутер 5G с SIM-картой (ALTEL 5G H155-380) | C42: шт. | D42: 1 | E42: =ROUND(36238/(1+НДС),0) -> 31240 | F42: разово | G42: 1 | I42: =IF(F42="разово",IF(G42<=3,D42*E42,0),IF(F42="мес",D42*E42*MAX(0,4-G42),D42*E42*MAX(0,4-G42)/12)) -> 31240 | J42: =IF($F42="разово",IF($M42=12,0,$I42),IF($F42="мес",$D42*$E42*(($G42<=1)+($G42<=2)),IF($F42="год",$D42*$E42/12*(($G42<=1)+($G42<=2)),$I42/2))) -> 31240 | K42: =IF($F42="разово",IF($M42=12,$I42,0),IF($F42="мес",$D42*$E42*($G42<=3),IF($F42="год",$D42*$E42/12*($G42<=3),$I42/2))) -> 0 | L42: =IF($F42="разово",0,IF($F42="мес",$D42*$E42*($G42<=3),IF($F42="год",$D42*$E42/12*($G42<=3),$I42/2))) -> 0 | M42: 11
A43: Оснащение | B43: Интерактивная панель 75" (доска-экран) для зала совещаний: 4K, сенсорная, Android (класс Iiyama ProLite TE7515A-B2AG) | C43: шт. | D43: 0 | E43: =ROUND(989997/(1+НДС),0) -> 853446 | F43: разово | G43: 1 | I43: =IF(F43="разово",IF(G43<=3,D43*E43,0),IF(F43="мес",D43*E43*MAX(0,4-G43),D43*E43*MAX(0,4-G43)/12)) -> 0 | J43: =IF($F43="разово",IF($M43=12,0,$I43),IF($F43="мес",$D43*$E43*(($G43<=1)+($G43<=2)),IF($F43="год",$D43*$E43/12*(($G43<=1)+($G43<=2)),$I43/2))) -> 0 | K43: =IF($F43="разово",IF($M43=12,$I43,0),IF($F43="мес",$D43*$E43*($G43<=3),IF($F43="год",$D43*$E43/12*($G43<=3),$I43/2))) -> 0 | L43: =IF($F43="разово",0,IF($F43="мес",$D43*$E43*($G43<=3),IF($F43="год",$D43*$E43/12*($G43<=3),$I43/2))) -> 0 | M43: 11
A44: Оснащение | B44: Мобильная стойка на колёсах под ТВ 40″ (Onkron TS1351, сталь SPCC, нагрузка 45,5 кг, 32–65″) | C44: шт. | D44: 1 | E44: =ROUND(56990/(1+НДС),0) -> 49129 | F44: разово | G44: 1 | I44: =IF(F44="разово",IF(G44<=3,D44*E44,0),IF(F44="мес",D44*E44*MAX(0,4-G44),D44*E44*MAX(0,4-G44)/12)) -> 49129 | J44: =IF($F44="разово",IF($M44=12,0,$I44),IF($F44="мес",$D44*$E44*(($G44<=1)+($G44<=2)),IF($F44="год",$D44*$E44/12*(($G44<=1)+($G44<=2)),$I44/2))) -> 49129 | K44: =IF($F44="разово",IF($M44=12,$I44,0),IF($F44="мес",$D44*$E44*($G44<=3),IF($F44="год",$D44*$E44/12*($G44<=3),$I44/2))) -> 0 | L44: =IF($F44="разово",0,IF($F44="мес",$D44*$E44*($G44<=3),IF($F44="год",$D44*$E44/12*($G44<=3),$I44/2))) -> 0 | M44: 11
A45: Оснащение | B45: Мобильная стойка на колёсах под тяжёлый телевизор (SK-200, нагрузка 101 кг, 55–86″, VESA до 800×600) | C45: шт. | D45: 1 | E45: =ROUND(111605/(1+НДС),0) -> 96211 | F45: разово | G45: 1 | I45: =IF(F45="разово",IF(G45<=3,D45*E45,0),IF(F45="мес",D45*E45*MAX(0,4-G45),D45*E45*MAX(0,4-G45)/12)) -> 96211 | J45: =IF($F45="разово",IF($M45=12,0,$I45),IF($F45="мес",$D45*$E45*(($G45<=1)+($G45<=2)),IF($F45="год",$D45*$E45/12*(($G45<=1)+($G45<=2)),$I45/2))) -> 0 | K45: =IF($F45="разово",IF($M45=12,$I45,0),IF($F45="мес",$D45*$E45*($G45<=3),IF($F45="год",$D45*$E45/12*($G45<=3),$I45/2))) -> 96211 | L45: =IF($F45="разово",0,IF($F45="мес",$D45*$E45*($G45<=3),IF($F45="год",$D45*$E45/12*($G45<=3),$I45/2))) -> 0 | M45: 12
A46: Оснащение | B46: Конференц-камера и спикерфон для зала совещаний, с установкой и настройкой | C46: компл. | D46: 1 | E46: 300000 | F46: разово | G46: 1 | I46: =IF(F46="разово",IF(G46<=3,D46*E46,0),IF(F46="мес",D46*E46*MAX(0,4-G46),D46*E46*MAX(0,4-G46)/12)) -> 300000 | J46: =IF($F46="разово",IF($M46=12,0,$I46),IF($F46="мес",$D46*$E46*(($G46<=1)+($G46<=2)),IF($F46="год",$D46*$E46/12*(($G46<=1)+($G46<=2)),$I46/2))) -> 0 | K46: =IF($F46="разово",IF($M46=12,$I46,0),IF($F46="мес",$D46*$E46*($G46<=3),IF($F46="год",$D46*$E46/12*($G46<=3),$I46/2))) -> 300000 | L46: =IF($F46="разово",0,IF($F46="мес",$D46*$E46*($G46<=3),IF($F46="год",$D46*$E46/12*($G46<=3),$I46/2))) -> 0 | M46: 12
A47: Оснащение | B47: Сетевое оборудование и СКС (роутер, коммутатор, Wi-Fi, монтаж) | C47: компл. | D47: 0 | E47: 800000 | F47: разово | G47: 1 | I47: =IF(F47="разово",IF(G47<=3,D47*E47,0),IF(F47="мес",D47*E47*MAX(0,4-G47),D47*E47*MAX(0,4-G47)/12)) -> 0 | J47: =IF($F47="разово",IF($M47=12,0,$I47),IF($F47="мес",$D47*$E47*(($G47<=1)+($G47<=2)),IF($F47="год",$D47*$E47/12*(($G47<=1)+($G47<=2)),$I47/2))) -> 0 | K47: =IF($F47="разово",IF($M47=12,$I47,0),IF($F47="мес",$D47*$E47*($G47<=3),IF($F47="год",$D47*$E47/12*($G47<=3),$I47/2))) -> 0 | L47: =IF($F47="разово",0,IF($F47="мес",$D47*$E47*($G47<=3),IF($F47="год",$D47*$E47/12*($G47<=3),$I47/2))) -> 0 | M47: 11
A48: Оснащение | B48: Сетевой накопитель (NAS) с дисками — архив фото/видео и документов | C48: шт. | D48: 0 | E48: 700000 | F48: разово | G48: 1 | I48: =IF(F48="разово",IF(G48<=3,D48*E48,0),IF(F48="мес",D48*E48*MAX(0,4-G48),D48*E48*MAX(0,4-G48)/12)) -> 0 | J48: =IF($F48="разово",IF($M48=12,0,$I48),IF($F48="мес",$D48*$E48*(($G48<=1)+($G48<=2)),IF($F48="год",$D48*$E48/12*(($G48<=1)+($G48<=2)),$I48/2))) -> 0 | K48: =IF($F48="разово",IF($M48=12,$I48,0),IF($F48="мес",$D48*$E48*($G48<=3),IF($F48="год",$D48*$E48/12*($G48<=3),$I48/2))) -> 0 | L48: =IF($F48="разово",0,IF($F48="мес",$D48*$E48*($G48<=3),IF($F48="год",$D48*$E48/12*($G48<=3),$I48/2))) -> 0 | M48: 11
A49: Оснащение | B49: Фото- и видеооборудование – базовый комплект (КП PSP Digital) | C49: смета | D49: 1 | E49: ='Смета фото-видео'!G24 -> 300000 | F49: разово | G49: 1 | I49: =IF(F49="разово",IF(G49<=3,D49*E49,0),IF(F49="мес",D49*E49*MAX(0,4-G49),D49*E49*MAX(0,4-G49)/12)) -> 300000 | J49: =IF($F49="разово",IF($M49=12,0,$I49),IF($F49="мес",$D49*$E49*(($G49<=1)+($G49<=2)),IF($F49="год",$D49*$E49/12*(($G49<=1)+($G49<=2)),$I49/2))) -> 0 | K49: =IF($F49="разово",IF($M49=12,$I49,0),IF($F49="мес",$D49*$E49*($G49<=3),IF($F49="год",$D49*$E49/12*($G49<=3),$I49/2))) -> 300000 | L49: =IF($F49="разово",0,IF($F49="мес",$D49*$E49*($G49<=3),IF($F49="год",$D49*$E49/12*($G49<=3),$I49/2))) -> 0 | M49: 12
A50: Оснащение | B50: Бытовая техника (кулер для воды, холодильник, микроволновка, кофемашина) | C50: компл. | D50: 1 | E50: 400000 | F50: разово | G50: 1 | I50: =IF(F50="разово",IF(G50<=3,D50*E50,0),IF(F50="мес",D50*E50*MAX(0,4-G50),D50*E50*MAX(0,4-G50)/12)) -> 400000 | J50: =IF($F50="разово",IF($M50=12,0,$I50),IF($F50="мес",$D50*$E50*(($G50<=1)+($G50<=2)),IF($F50="год",$D50*$E50/12*(($G50<=1)+($G50<=2)),$I50/2))) -> 400000 | K50: =IF($F50="разово",IF($M50=12,$I50,0),IF($F50="мес",$D50*$E50*($G50<=3),IF($F50="год",$D50*$E50/12*($G50<=3),$I50/2))) -> 0 | L50: =IF($F50="разово",0,IF($F50="мес",$D50*$E50*($G50<=3),IF($F50="год",$D50*$E50/12*($G50<=3),$I50/2))) -> 0 | M50: 11
A51: Оснащение | B51: Второй кулер для воды, напольный, нагрев и охлаждение (класс Midea MK-32H) | C51: шт. | D51: 1 | E51: =ROUND(35990/(1+НДС),0) -> 31026 | F51: разово | G51: 1 | I51: =IF(F51="разово",IF(G51<=3,D51*E51,0),IF(F51="мес",D51*E51*MAX(0,4-G51),D51*E51*MAX(0,4-G51)/12)) -> 31026 | J51: =IF($F51="разово",IF($M51=12,0,$I51),IF($F51="мес",$D51*$E51*(($G51<=1)+($G51<=2)),IF($F51="год",$D51*$E51/12*(($G51<=1)+($G51<=2)),$I51/2))) -> 31026 | K51: =IF($F51="разово",IF($M51=12,$I51,0),IF($F51="мес",$D51*$E51*($G51<=3),IF($F51="год",$D51*$E51/12*($G51<=3),$I51/2))) -> 0 | L51: =IF($F51="разово",0,IF($F51="мес",$D51*$E51*($G51<=3),IF($F51="год",$D51*$E51/12*($G51<=3),$I51/2))) -> 0 | M51: 11
A52: Оснащение | B52: Стул офисный для посетителей (ZETA СМ 6 серый, скруглённая спинка, каркас металл, обивка рогожка) | C52: шт. | D52: 20 | E52: =ROUND(7595/(1+НДС),0) -> 6547 | F52: разово | G52: 1 | I52: =IF(F52="разово",IF(G52<=3,D52*E52,0),IF(F52="мес",D52*E52*MAX(0,4-G52),D52*E52*MAX(0,4-G52)/12)) -> 130940 | J52: =IF($F52="разово",IF($M52=12,0,$I52),IF($F52="мес",$D52*$E52*(($G52<=1)+($G52<=2)),IF($F52="год",$D52*$E52/12*(($G52<=1)+($G52<=2)),$I52/2))) -> 130940 | K52: =IF($F52="разово",IF($M52=12,$I52,0),IF($F52="мес",$D52*$E52*($G52<=3),IF($F52="год",$D52*$E52/12*($G52<=3),$I52/2))) -> 0 | L52: =IF($F52="разово",0,IF($F52="мес",$D52*$E52*($G52<=3),IF($F52="год",$D52*$E52/12*($G52<=3),$I52/2))) -> 0 | M52: 11
A53: Оснащение | B53: Жалюзи вертикальные тканевые с установкой (зона 710) | C53: компл. | D53: 1 | E53: =ROUND(428736/(1+НДС),0) -> 369600 | F53: разово | G53: 1 | I53: =IF(F53="разово",IF(G53<=3,D53*E53,0),IF(F53="мес",D53*E53*MAX(0,4-G53),D53*E53*MAX(0,4-G53)/12)) -> 369600 | J53: =IF($F53="разово",IF($M53=12,0,$I53),IF($F53="мес",$D53*$E53*(($G53<=1)+($G53<=2)),IF($F53="год",$D53*$E53/12*(($G53<=1)+($G53<=2)),$I53/2))) -> 369600 | K53: =IF($F53="разово",IF($M53=12,$I53,0),IF($F53="мес",$D53*$E53*($G53<=3),IF($F53="год",$D53*$E53/12*($G53<=3),$I53/2))) -> 0 | L53: =IF($F53="разово",0,IF($F53="мес",$D53*$E53*($G53<=3),IF($F53="год",$D53*$E53/12*($G53<=3),$I53/2))) -> 0 | M53: 11
A54: Оснащение | B54: Декоративное растение напольное в высоком кашпо | C54: шт. | D54: 3 | E54: =ROUND(30701/(1+НДС),0) -> 26466 | F54: разово | G54: 1 | I54: =IF(F54="разово",IF(G54<=3,D54*E54,0),IF(F54="мес",D54*E54*MAX(0,4-G54),D54*E54*MAX(0,4-G54)/12)) -> 79398 | J54: =IF($F54="разово",IF($M54=12,0,$I54),IF($F54="мес",$D54*$E54*(($G54<=1)+($G54<=2)),IF($F54="год",$D54*$E54/12*(($G54<=1)+($G54<=2)),$I54/2))) -> 0 | K54: =IF($F54="разово",IF($M54=12,$I54,0),IF($F54="мес",$D54*$E54*($G54<=3),IF($F54="год",$D54*$E54/12*($G54<=3),$I54/2))) -> 79398 | L54: =IF($F54="разово",0,IF($F54="мес",$D54*$E54*($G54<=3),IF($F54="год",$D54*$E54/12*($G54<=3),$I54/2))) -> 0 | M54: 12
A55: Оснащение | B55: Лицензии 1С на дополнительные рабочие места | C55: компл. | D55: 1 | E55: 150000 | F55: разово | G55: 1 | I55: =IF(F55="разово",IF(G55<=3,D55*E55,0),IF(F55="мес",D55*E55*MAX(0,4-G55),D55*E55*MAX(0,4-G55)/12)) -> 150000 | J55: =IF($F55="разово",IF($M55=12,0,$I55),IF($F55="мес",$D55*$E55*(($G55<=1)+($G55<=2)),IF($F55="год",$D55*$E55/12*(($G55<=1)+($G55<=2)),$I55/2))) -> 150000 | K55: =IF($F55="разово",IF($M55=12,$I55,0),IF($F55="мес",$D55*$E55*($G55<=3),IF($F55="год",$D55*$E55/12*($G55<=3),$I55/2))) -> 0 | L55: =IF($F55="разово",0,IF($F55="мес",$D55*$E55*($G55<=3),IF($F55="год",$D55*$E55/12*($G55<=3),$I55/2))) -> 0 | M55: 11
A56: Оснащение | B56: Вывеска и брендирование офиса | C56: компл. | D56: 1 | E56: 400000 | F56: разово | G56: 1 | I56: =IF(F56="разово",IF(G56<=3,D56*E56,0),IF(F56="мес",D56*E56*MAX(0,4-G56),D56*E56*MAX(0,4-G56)/12)) -> 400000 | J56: =IF($F56="разово",IF($M56=12,0,$I56),IF($F56="мес",$D56*$E56*(($G56<=1)+($G56<=2)),IF($F56="год",$D56*$E56/12*(($G56<=1)+($G56<=2)),$I56/2))) -> 0 | K56: =IF($F56="разово",IF($M56=12,$I56,0),IF($F56="мес",$D56*$E56*($G56<=3),IF($F56="год",$D56*$E56/12*($G56<=3),$I56/2))) -> 400000 | L56: =IF($F56="разово",0,IF($F56="мес",$D56*$E56*($G56<=3),IF($F56="год",$D56*$E56/12*($G56<=3),$I56/2))) -> 0 | M56: 12
A57: Оснащение | B57: Аптечки | C57: шт. | D57: 1 | E57: 10000 | F57: разово | G57: 1 | I57: =IF(F57="разово",IF(G57<=3,D57*E57,0),IF(F57="мес",D57*E57*MAX(0,4-G57),D57*E57*MAX(0,4-G57)/12)) -> 10000 | J57: =IF($F57="разово",IF($M57=12,0,$I57),IF($F57="мес",$D57*$E57*(($G57<=1)+($G57<=2)),IF($F57="год",$D57*$E57/12*(($G57<=1)+($G57<=2)),$I57/2))) -> 10000 | K57: =IF($F57="разово",IF($M57=12,$I57,0),IF($F57="мес",$D57*$E57*($G57<=3),IF($F57="год",$D57*$E57/12*($G57<=3),$I57/2))) -> 0 | L57: =IF($F57="разово",0,IF($F57="мес",$D57*$E57*($G57<=3),IF($F57="год",$D57*$E57/12*($G57<=3),$I57/2))) -> 0 | M57: 11
A58: Офис | B58: Аренда офиса | C58: мес. | D58: 1 | E58: =Аренда_мес -> 4869152.1 | F58: мес | G58: 1 | I58: =D58*E58*Аренда_мес_2026 -> 11466068 | J58: =$D58*$E58*(Аренда_мес_2026-1) -> 6596915.7 | K58: =IF($F58="разово",IF($M58=12,$I58,0),IF($F58="мес",$D58*$E58*($G58<=3),IF($F58="год",$D58*$E58/12*($G58<=3),$I58/2))) -> 4869152.1 | L58: =IF($F58="разово",0,IF($F58="мес",$D58*$E58*($G58<=3),IF($F58="год",$D58*$E58/12*($G58<=3),$I58/2))) -> 4869152.1
A59: Офис | B59: Гарантийный депозит по аренде (1 месячная ставка, возвратный) | C59: депозит | D59: 1 | E59: =Аренда_мес*Депозит_мес -> 4869152.1 | F59: разово | G59: 1 | I59: =IF(F59="разово",IF(G59<=3,D59*E59,0),IF(F59="мес",D59*E59*MAX(0,4-G59),D59*E59*MAX(0,4-G59)/12)) -> 4869152.1 | J59: =IF($F59="разово",IF($M59=12,0,$I59),IF($F59="мес",$D59*$E59*(($G59<=1)+($G59<=2)),IF($F59="год",$D59*$E59/12*(($G59<=1)+($G59<=2)),$I59/2))) -> 4869152.1 | K59: =IF($F59="разово",IF($M59=12,$I59,0),IF($F59="мес",$D59*$E59*($G59<=3),IF($F59="год",$D59*$E59/12*($G59<=3),$I59/2))) -> 0 | L59: =IF($F59="разово",0,IF($F59="мес",$D59*$E59*($G59<=3),IF($F59="год",$D59*$E59/12*($G59<=3),$I59/2))) -> 0 | M59: 11
A60: Офис | B60: Текущий мелкий ремонт и хозяйственные расходы | C60: мес. | D60: 1 | E60: 100000 | F60: мес | G60: 2 | I60: =IF(F60="разово",IF(G60<=3,D60*E60,0),IF(F60="мес",D60*E60*MAX(0,4-G60),D60*E60*MAX(0,4-G60)/12)) -> 200000 | J60: =IF($F60="разово",IF($M60=12,0,$I60),IF($F60="мес",$D60*$E60*(($G60<=1)+($G60<=2)),IF($F60="год",$D60*$E60/12*(($G60<=1)+($G60<=2)),$I60/2))) -> 100000 | K60: =IF($F60="разово",IF($M60=12,$I60,0),IF($F60="мес",$D60*$E60*($G60<=3),IF($F60="год",$D60*$E60/12*($G60<=3),$I60/2))) -> 100000 | L60: =IF($F60="разово",0,IF($F60="мес",$D60*$E60*($G60<=3),IF($F60="год",$D60*$E60/12*($G60<=3),$I60/2))) -> 100000
A61: Офис | B61: Курьерские и почтовые услуги (МЭПР, акиматы, партнёры) | C61: мес. | D61: 1 | E61: 30000 | F61: мес | G61: 2 | I61: =IF(F61="разово",IF(G61<=3,D61*E61,0),IF(F61="мес",D61*E61*MAX(0,4-G61),D61*E61*MAX(0,4-G61)/12)) -> 60000 | J61: =IF($F61="разово",IF($M61=12,0,$I61),IF($F61="мес",$D61*$E61*(($G61<=1)+($G61<=2)),IF($F61="год",$D61*$E61/12*(($G61<=1)+($G61<=2)),$I61/2))) -> 30000 | K61: =IF($F61="разово",IF($M61=12,$I61,0),IF($F61="мес",$D61*$E61*($G61<=3),IF($F61="год",$D61*$E61/12*($G61<=3),$I61/2))) -> 30000 | L61: =IF($F61="разово",0,IF($F61="мес",$D61*$E61*($G61<=3),IF($F61="год",$D61*$E61/12*($G61<=3),$I61/2))) -> 30000
A62: Офис | B62: Интернет (выделенный канал) | C62: мес. | D62: 1 | E62: 50000 | F62: мес | G62: 2 | I62: =IF(F62="разово",IF(G62<=3,D62*E62,0),IF(F62="мес",D62*E62*MAX(0,4-G62),D62*E62*MAX(0,4-G62)/12)) -> 100000 | J62: =IF($F62="разово",IF($M62=12,0,$I62),IF($F62="мес",$D62*$E62*(($G62<=1)+($G62<=2)),IF($F62="год",$D62*$E62/12*(($G62<=1)+($G62<=2)),$I62/2))) -> 50000 | K62: =IF($F62="разово",IF($M62=12,$I62,0),IF($F62="мес",$D62*$E62*($G62<=3),IF($F62="год",$D62*$E62/12*($G62<=3),$I62/2))) -> 50000 | L62: =IF($F62="разово",0,IF($F62="мес",$D62*$E62*($G62<=3),IF($F62="год",$D62*$E62/12*($G62<=3),$I62/2))) -> 50000
A63: Офис | B63: Мобильный интернет для двух Wi-Fi роутеров, безлимит на максимальной скорости (ALTEL, тариф «Шаңырақ») | C63: роутер | D63: 2 | E63: =ROUND(5490/(1+НДС),0) -> 4733 | F63: мес | G63: 2 | I63: =IF(F63="разово",IF(G63<=3,D63*E63,0),IF(F63="мес",D63*E63*MAX(0,4-G63),D63*E63*MAX(0,4-G63)/12)) -> 18932 | J63: =IF($F63="разово",IF($M63=12,0,$I63),IF($F63="мес",$D63*$E63*(($G63<=1)+($G63<=2)),IF($F63="год",$D63*$E63/12*(($G63<=1)+($G63<=2)),$I63/2))) -> 9466 | K63: =IF($F63="разово",IF($M63=12,$I63,0),IF($F63="мес",$D63*$E63*($G63<=3),IF($F63="год",$D63*$E63/12*($G63<=3),$I63/2))) -> 9466 | L63: =IF($F63="разово",0,IF($F63="мес",$D63*$E63*($G63<=3),IF($F63="год",$D63*$E63/12*($G63<=3),$I63/2))) -> 9466
A64: Офис | B64: Обслуживание МФУ и расходники | C64: мес. | D64: 1 | E64: 30000 | F64: мес | G64: 2 | I64: =IF(F64="разово",IF(G64<=3,D64*E64,0),IF(F64="мес",D64*E64*MAX(0,4-G64),D64*E64*MAX(0,4-G64)/12)) -> 60000 | J64: =IF($F64="разово",IF($M64=12,0,$I64),IF($F64="мес",$D64*$E64*(($G64<=1)+($G64<=2)),IF($F64="год",$D64*$E64/12*(($G64<=1)+($G64<=2)),$I64/2))) -> 30000 | K64: =IF($F64="разово",IF($M64=12,$I64,0),IF($F64="мес",$D64*$E64*($G64<=3),IF($F64="год",$D64*$E64/12*($G64<=3),$I64/2))) -> 30000 | L64: =IF($F64="разово",0,IF($F64="мес",$D64*$E64*($G64<=3),IF($F64="год",$D64*$E64/12*($G64<=3),$I64/2))) -> 30000
A65: Офис | B65: Канцелярия и бумага – ежемесячно (лист «Канцелярия») | C65: мес. | D65: 1 | E65: =Канцелярия!F11 -> 24125 | F65: мес | G65: 2 | I65: =IF(F65="разово",IF(G65<=3,D65*E65,0),IF(F65="мес",D65*E65*MAX(0,4-G65),D65*E65*MAX(0,4-G65)/12)) -> 48250 | J65: =IF($F65="разово",IF($M65=12,0,$I65),IF($F65="мес",$D65*$E65*(($G65<=1)+($G65<=2)),IF($F65="год",$D65*$E65/12*(($G65<=1)+($G65<=2)),$I65/2))) -> 24125 | K65: =IF($F65="разово",IF($M65=12,$I65,0),IF($F65="мес",$D65*$E65*($G65<=3),IF($F65="год",$D65*$E65/12*($G65<=3),$I65/2))) -> 24125 | L65: =IF($F65="разово",0,IF($F65="мес",$D65*$E65*($G65<=3),IF($F65="год",$D65*$E65/12*($G65<=3),$I65/2))) -> 24125
A66: Офис | B66: Канцелярские принадлежности при открытии офиса (лист «Канцелярия») | C66: компл. | D66: 1 | E66: =Канцелярия!F21 -> 20048 | F66: разово | G66: 1 | I66: =IF(F66="разово",IF(G66<=3,D66*E66,0),IF(F66="мес",D66*E66*MAX(0,4-G66),D66*E66*MAX(0,4-G66)/12)) -> 20048 | J66: =IF($F66="разово",IF($M66=12,0,$I66),IF($F66="мес",$D66*$E66*(($G66<=1)+($G66<=2)),IF($F66="год",$D66*$E66/12*(($G66<=1)+($G66<=2)),$I66/2))) -> 20048 | K66: =IF($F66="разово",IF($M66=12,$I66,0),IF($F66="мес",$D66*$E66*($G66<=3),IF($F66="год",$D66*$E66/12*($G66<=3),$I66/2))) -> 0 | L66: =IF($F66="разово",0,IF($F66="мес",$D66*$E66*($G66<=3),IF($F66="год",$D66*$E66/12*($G66<=3),$I66/2))) -> 0 | M66: 11
A67: Офис | B67: Представительские расходы (встречи, кофе-брейки) | C67: мес. | D67: 1 | E67: 100000 | F67: мес | G67: 2 | I67: =IF(F67="разово",IF(G67<=3,D67*E67,0),IF(F67="мес",D67*E67*MAX(0,4-G67),D67*E67*MAX(0,4-G67)/12)) -> 200000 | J67: =IF($F67="разово",IF($M67=12,0,$I67),IF($F67="мес",$D67*$E67*(($G67<=1)+($G67<=2)),IF($F67="год",$D67*$E67/12*(($G67<=1)+($G67<=2)),$I67/2))) -> 100000 | K67: =IF($F67="разово",IF($M67=12,$I67,0),IF($F67="мес",$D67*$E67*($G67<=3),IF($F67="год",$D67*$E67/12*($G67<=3),$I67/2))) -> 100000 | L67: =IF($F67="разово",0,IF($F67="мес",$D67*$E67*($G67<=3),IF($F67="год",$D67*$E67/12*($G67<=3),$I67/2))) -> 100000
A68: Цифровые | B68: Microsoft 365 Business Standard (почта, Teams, OneDrive) | C68: польз. | D68: 19 | E68: 7000 | F68: мес | G68: 2 | I68: =IF(F68="разово",IF(G68<=3,D68*E68,0),IF(F68="мес",D68*E68*MAX(0,4-G68),D68*E68*MAX(0,4-G68)/12)) -> 266000 | J68: =IF($F68="разово",IF($M68=12,0,$I68),IF($F68="мес",$D68*$E68*(($G68<=1)+($G68<=2)),IF($F68="год",$D68*$E68/12*(($G68<=1)+($G68<=2)),$I68/2))) -> 133000 | K68: =IF($F68="разово",IF($M68=12,$I68,0),IF($F68="мес",$D68*$E68*($G68<=3),IF($F68="год",$D68*$E68/12*($G68<=3),$I68/2))) -> 133000 | L68: =IF($F68="разово",0,IF($F68="мес",$D68*$E68*($G68<=3),IF($F68="год",$D68*$E68/12*($G68<=3),$I68/2))) -> 133000
A69: Цифровые | B69: Power BI Pro (дашборды) | C69: польз. | D69: 3 | E69: 7500 | F69: мес | G69: 2 | I69: =IF(F69="разово",IF(G69<=3,D69*E69,0),IF(F69="мес",D69*E69*MAX(0,4-G69),D69*E69*MAX(0,4-G69)/12)) -> 45000 | J69: =IF($F69="разово",IF($M69=12,0,$I69),IF($F69="мес",$D69*$E69*(($G69<=1)+($G69<=2)),IF($F69="год",$D69*$E69/12*(($G69<=1)+($G69<=2)),$I69/2))) -> 22500 | K69: =IF($F69="разово",IF($M69=12,$I69,0),IF($F69="мес",$D69*$E69*($G69<=3),IF($F69="год",$D69*$E69/12*($G69<=3),$I69/2))) -> 22500 | L69: =IF($F69="разово",0,IF($F69="мес",$D69*$E69*($G69<=3),IF($F69="год",$D69*$E69/12*($G69<=3),$I69/2))) -> 22500
A70: Цифровые | B70: Canva Teams / Adobe CC (дизайн) | C70: лиц. | D70: 2 | E70: 30000 | F70: мес | G70: 2 | I70: =IF(F70="разово",IF(G70<=3,D70*E70,0),IF(F70="мес",D70*E70*MAX(0,4-G70),D70*E70*MAX(0,4-G70)/12)) -> 120000 | J70: =IF($F70="разово",IF($M70=12,0,$I70),IF($F70="мес",$D70*$E70*(($G70<=1)+($G70<=2)),IF($F70="год",$D70*$E70/12*(($G70<=1)+($G70<=2)),$I70/2))) -> 60000 | K70: =IF($F70="разово",IF($M70=12,$I70,0),IF($F70="мес",$D70*$E70*($G70<=3),IF($F70="год",$D70*$E70/12*($G70<=3),$I70/2))) -> 60000 | L70: =IF($F70="разово",0,IF($F70="мес",$D70*$E70*($G70<=3),IF($F70="год",$D70*$E70/12*($G70<=3),$I70/2))) -> 60000
A71: Цифровые | B71: Zoom, тариф «Профессиональный» – годовая подписка (ВКС с регионами) | C71: лиц. | D71: 1 | E71: =ROUND(149.9*Курс,0) -> 79447 | F71: разово | G71: 2 | I71: =IF(F71="разово",IF(G71<=3,D71*E71,0),IF(F71="мес",D71*E71*MAX(0,4-G71),D71*E71*MAX(0,4-G71)/12)) -> 79447 | J71: =IF($F71="разово",IF($M71=12,0,$I71),IF($F71="мес",$D71*$E71*(($G71<=1)+($G71<=2)),IF($F71="год",$D71*$E71/12*(($G71<=1)+($G71<=2)),$I71/2))) -> 79447 | K71: =IF($F71="разово",IF($M71=12,$I71,0),IF($F71="мес",$D71*$E71*($G71<=3),IF($F71="год",$D71*$E71/12*($G71<=3),$I71/2))) -> 0 | L71: =IF($F71="разово",0,IF($F71="мес",$D71*$E71*($G71<=3),IF($F71="год",$D71*$E71/12*($G71<=3),$I71/2))) -> 0 | M71: 11
A72: Цифровые | B72: Битрикс24, тариф «Стандартный» (до 50 пользователей): CRM, задачи, проекты, диск, чат | C72: подписка | D72: 1 | E72: 38000 | F72: мес | G72: 2 | I72: =IF(F72="разово",IF(G72<=3,D72*E72,0),IF(F72="мес",D72*E72*MAX(0,4-G72),D72*E72*MAX(0,4-G72)/12)) -> 76000 | J72: =IF($F72="разово",IF($M72=12,0,$I72),IF($F72="мес",$D72*$E72*(($G72<=1)+($G72<=2)),IF($F72="год",$D72*$E72/12*(($G72<=1)+($G72<=2)),$I72/2))) -> 38000 | K72: =IF($F72="разово",IF($M72=12,$I72,0),IF($F72="мес",$D72*$E72*($G72<=3),IF($F72="год",$D72*$E72/12*($G72<=3),$I72/2))) -> 38000 | L72: =IF($F72="разово",0,IF($F72="мес",$D72*$E72*($G72<=3),IF($F72="год",$D72*$E72/12*($G72<=3),$I72/2))) -> 38000
A73: Медиа | B73: Таргетированная реклама (продвижение в соцсетях) | C73: сумма | F73: по ПО | I73: 2000000 | J73: =IF($F73="разово",IF($M73=12,0,$I73),IF($F73="мес",$D73*$E73*(($G73<=1)+($G73<=2)),IF($F73="год",$D73*$E73/12*(($G73<=1)+($G73<=2)),$I73/2))) -> 1000000 | K73: =IF($F73="разово",IF($M73=12,$I73,0),IF($F73="мес",$D73*$E73*($G73<=3),IF($F73="год",$D73*$E73/12*($G73<=3),$I73/2))) -> 1000000 | L73: =IF($F73="разово",0,IF($F73="мес",$D73*$E73*($G73<=3),IF($F73="год",$D73*$E73/12*($G73<=3),$I73/2))) -> 1000000
A74: Медиа | B74: Полиграфия и брендированная продукция | C74: мес. | D74: 1 | E74: 150000 | F74: мес | G74: 2 | I74: =IF(F74="разово",IF(G74<=3,D74*E74,0),IF(F74="мес",D74*E74*MAX(0,4-G74),D74*E74*MAX(0,4-G74)/12)) -> 300000 | J74: =IF($F74="разово",IF($M74=12,0,$I74),IF($F74="мес",$D74*$E74*(($G74<=1)+($G74<=2)),IF($F74="год",$D74*$E74/12*(($G74<=1)+($G74<=2)),$I74/2))) -> 150000 | K74: =IF($F74="разово",IF($M74=12,$I74,0),IF($F74="мес",$D74*$E74*($G74<=3),IF($F74="год",$D74*$E74/12*($G74<=3),$I74/2))) -> 150000 | L74: =IF($F74="разово",0,IF($F74="мес",$D74*$E74*($G74<=3),IF($F74="год",$D74*$E74/12*($G74<=3),$I74/2))) -> 150000
A75: Медиа | B75: Фотобанк, музыка (подписки) | C75: мес. | D75: 1 | E75: 25000 | F75: мес | G75: 2 | I75: =IF(F75="разово",IF(G75<=3,D75*E75,0),IF(F75="мес",D75*E75*MAX(0,4-G75),D75*E75*MAX(0,4-G75)/12)) -> 50000 | J75: =IF($F75="разово",IF($M75=12,0,$I75),IF($F75="мес",$D75*$E75*(($G75<=1)+($G75<=2)),IF($F75="год",$D75*$E75/12*(($G75<=1)+($G75<=2)),$I75/2))) -> 25000 | K75: =IF($F75="разово",IF($M75=12,$I75,0),IF($F75="мес",$D75*$E75*($G75<=3),IF($F75="год",$D75*$E75/12*($G75<=3),$I75/2))) -> 25000 | L75: =IF($F75="разово",0,IF($F75="мес",$D75*$E75*($G75<=3),IF($F75="год",$D75*$E75/12*($G75<=3),$I75/2))) -> 25000
A76: Офис | B76: Нотариальные расходы и пострегистрационные услуги МФЦА | C76: компл. | D76: 1 | E76: 350000 | F76: разово | G76: 1 | I76: =IF(F76="разово",IF(G76<=3,D76*E76,0),IF(F76="мес",D76*E76*MAX(0,4-G76),D76*E76*MAX(0,4-G76)/12)) -> 350000 | J76: =IF($F76="разово",IF($M76=12,0,$I76),IF($F76="мес",$D76*$E76*(($G76<=1)+($G76<=2)),IF($F76="год",$D76*$E76/12*(($G76<=1)+($G76<=2)),$I76/2))) -> 350000 | K76: =IF($F76="разово",IF($M76=12,$I76,0),IF($F76="мес",$D76*$E76*($G76<=3),IF($F76="год",$D76*$E76/12*($G76<=3),$I76/2))) -> 0 | L76: =IF($F76="разово",0,IF($F76="мес",$D76*$E76*($G76<=3),IF($F76="год",$D76*$E76/12*($G76<=3),$I76/2))) -> 0 | M76: 11

Sheet Проекты
A1: Первоочередные проекты на октябрь–декабрь 2026 года, ₸
A4: Раздел | B4: Статья | C4: Ед. | D4: Кол-во | E4: Цена, ₸ | F4: Тип | G4: Окт–дек 2026 | H4: Ноябрь 2026 | I4: Декабрь 2026 | J4: Январь 2027
A5: Проекты | B5: Реализация проекта «TAZA TALQY» (проведение встреч в регионах с жителями, молодежью) | C5: сумма | F5: по ПО | G5: ='Taza talqy'!F12 -> 10755520 | H5: =$G5*1/3 -> 3585173.3 | I5: =$G5*1/3 -> 3585173.3 | J5: =$G5*1/3 -> 3585173.3
A6: Проекты | B6: Презентация / запуск деятельности Проектного офиса | C6: сумма | F6: по ПО | G6: ='Презентация офисе'!F15 -> 6414800 | H6: =$G6*1 -> 6414800 | I6: =$G6*0 -> 0 | J6: =$G6*0 -> 0
A7: Проекты | B7: Реализация специальных / креативных проектов | C7: сумма | F7: по ПО | G7: ='креативные проекты'!F9 -> 17284000 | H7: =$G7*1/3 -> 5761333.3 | I7: =$G7*1/3 -> 5761333.3 | J7: =$G7*1/3 -> 5761333.3
A8: Проекты | B8: Информационное сопровождение проектов и деятельности | C8: сумма | F8: по ПО | G8: ='Информ сопровождение'!F13 -> 23432000 | H8: =$G8*1/3 -> 7810666.7 | I8: =$G8*1/3 -> 7810666.7 | J8: =$G8*1/3 -> 7810666.7
A9: Проекты | B9: Проведение социологического исследования | C9: сумма | F9: по ПО | G9: ='Соц исследования'!F8 -> 13108000 | H9: =$G9*1/2 -> 6554000 | I9: =$G9*1/2 -> 6554000 | J9: =$G9*0 -> 0
A10: Проекты | B10: Первый этап разработки цифровой платформы | C10: сумма | F10: по ПО | G10: ='Разработка платформы'!F7 -> 16240000 | H10: =$G10*1/2 -> 8120000 | I10: =$G10*1/2 -> 8120000 | J10: =$G10*0 -> 0
B13: ИТОГО первоочередные проекты | G13: =SUM(G5:G11) -> 87234320 | H13: =SUM(H5:H11) -> 38245973 | I13: =SUM(I5:I11) -> 31831173 | J13: =SUM(J5:J11) -> 17157173

Sheet Taza talqy
A1: Смета расходов по реализации проекта «TAZA TALQY» (в 6 регионах:ноябрь-январь)
A3: № | B3: Статьи затрат | C3: Единица измерения | D3: Количество | E3: Сумма за единицу, тенге | F3: Общая сумма, тыс.тенге
B4: Всего расходов | F4: =F11 -> 9272000
A5: 1. | B5: Проезд организаоторов и спикеров (туда и обратно) 4 человек*6 региона | C5: человек | D5: 56 | E5: 30000 | F5: =E5*D5 -> 1680000
A6: 2. | B6: Услуга по проживанию в гостинице 4 человек*8 региона*2 ночь | C6: услуга | D6: 56 | E6: 25000 | F6: =E6*D6 -> 1400000
A7: 3. | B7: Услуга по фото и видеосъёмке мероприятия | C7: услуга | D7: 6 | E7: 100000 | F7: =E7*D7 -> 600000
A8: 4. | B8: Продвижение в соцсетях (привлечение инфлюенсеров) | C8: услуга | D8: 6 | E8: 400000 | F8: =E8*D8 -> 2400000
A9: 5. | B9: Амбассадор-модератор проекта | C9: услуга | D9: 6 | E9: 500000 | F9: =E9*D9 -> 3000000
A10: 6. | B10: Обед/ужин спикеров | C10: услуга | D10: 48 | E10: 4000 | F10: =E10*D10 -> 192000
B11: ИТОГО без НДС | F11: =SUM(F5:F10) -> 9272000
B12: Всего расходов с НДС | F12: =F11*1.16 -> 10755520

Sheet Презентация офисе
A1: Смета расходов по проведению презентации/старта работы Проектного офиса (Астана, на 100 человек, ноябрь)
A3: № | B3: Статьи затрат | C3: Единица измерения | D3: Количество | E3: Сумма за единицу, тенге | F3: Общая сумма, тыс.тенге
B4: Всего расходов | F4: =F14 -> 5530000
A5: 1. | B5: Аренда площадки | C5: день | D5: 1 | E5: 500000 | F5: =E5*D5 -> 500000
A6: 2. | B6: Аренда оборудования, ЛЭД, колонки и усилитель (комплект),световое оборудование,кликер, доставка, монтаж, микрофоны, петличные микрофоны для спикеров | C6: день | D6: 1 | E6: 1500000 | F6: =E6*D6 -> 1500000
A7: 3. | B7: Видеозапись и фото мероприятия | C7: день | D7: 1 | E7: 100000 | F7: =E7*D7 -> 100000
A8: 4. | B8: Декорации и оформление фотозоны (фотозона размером 3м*6м с установкой, арт-зона с демонтажом и доставкой) | C8: услуга | D8: 1 | E8: 500000 | F8: =D8*E8 -> 500000
A9: 5. | B9: Печатная продукция (TAZA KIT: стикерпаки, букмарк, Карточка «5 привычек чистоты» и др.) | C9: штук | D9: 100 | E9: 3000 | F9: =D9*E9 -> 300000
A10: 6. | B10: Услуга по организации кофе-брейка (100 участников* 8 500 тг) | C10: штук | D10: 100 | E10: 7000 | F10: =D10*E10 -> 700000
B11: Фотобудка (3 часа, classic) | C11: штук | D11: 1 | E11: 130000 | F11: =D11*E11 -> 130000
A12: 6. | B12: Продвижение в соцсетях (привлечение инфлюенсеров) | C12: услуга | D12: 4 | E12: 400000 | F12: =D12*E12 -> 1600000
A13: 7. | B13: Ведущий | C13: человек | D13: 1 | E13: 200000 | F13: =E13*D13 -> 200000
B14: ИТОГО без НДС | F14: =SUM(F5:F13) -> 5530000
B15: Всего расходов с НДС | F15: =F14*1.16 -> 6414800

Sheet креативные проекты
A1: Смета расходов по реализации специальных / креативных проектов (ноябрь-январь)
A3: № | B3: Статьи затрат | C3: Единица измерения | D3: Количество | E3: Сумма за единицу, тенге | F3: Общая сумма, тыс.тенге
B4: Всего расходов | F4: =F8 -> 14900000
A5: 1. | B5: YouTube-проект «Taza niet» | C5: выпуск | D5: 4 | E5: 1100000 | F5: =E5*D5 -> 4400000
A6: 2. | B6: Совместный проект с амбассадором ByDastan | C6: проект | D6: 1 | E6: 6500000 | F6: =E6*D6 -> 6500000
A7: 3. | B7: Совместный проект с амбассадором Алия Ашим | C7: проект | D7: 1 | E7: 4000000 | F7: =E7*D7 -> 4000000
B8: ИТОГО без НДС | F8: =SUM(F5:F7) -> 14900000
B9: Всего расходов с НДС | F9: =F8*1.16 -> 17284000

Sheet Информ сопровождение
A1: Информационное сопровождение проектов и деятельности (ноябрь-январь)
A3: № | B3: Статьи затрат | C3: Единица измерения | D3: Количество | E3: Сумма за единицу, тенге | F3: Общая сумма, тыс.тенге
B4: Всего расходов | F4: =F12 -> 20200000
A5: 1. | B5: Продвижение проекта Таза пакет в соцсетях (привлечение инфлюенсеров) | C5: услуга | D5: 6 | E5: 400000 | F5: =E5*D5 -> 2400000
A6: 2. | B6: Изготовление видеороликов (ИИ ролики, промо, отчетные, интервью/подкаст в студии: съемки, монтаж, продвижение) | C6: выпуск | D6: 1 | E6: 3500000 | F6: =E6*D6 -> 3500000
A7: 3. | B7: Изготовление печатной продукции (бомберы, кепки, жилетки и др) | C7: услуга | D7: 1 | E7: 1500000 | F7: =E7*D7 -> 1500000
A8: 4. | B8: Ведение специальных инстаграм/тикток/тредс страниц (3 страницы*3 месяца) | C8: услуга | D8: 9 | E8: 800000 | F8: =D8*E8 -> 7200000
A9: 5. | B9: Проект "Менің таза әдетім" c UGC блогерами (4 блогера*4 публикаций*2 месяца) | C9: услуга | D9: 32 | E9: 100000 | F9: =D9*E9 -> 3200000
A10: 6. | B10: Продвижение проекта Taza team в соцсетях (привлечение инфлюенсеров) | C10: услуга | D10: 3 | E10: 400000 | F10: =E10*D10 -> 1200000
A11: 7. | B11: Изготовление маскота Tazabek (ростовая кукла) | C11: штук | D11: 3 | E11: 400000 | F11: =E11*D11 -> 1200000
B12: ИТОГО без НДС | F12: =SUM(F5:F11) -> 20200000
B13: Всего расходов с НДС | F13: =F12*1.16 -> 23432000

Sheet Соц исследования
A1: Проведение социологического исследования (ноябрь-декабрь)
A3: № | B3: Статьи затрат | C3: Единица измерения | D3: Количество | E3: Сумма за единицу, тенге | F3: Общая сумма, тыс.тенге
B4: Всего расходов | F4: =F7 -> 11300000
A5: 1. | B5: Проведение комплексного социологического исследования | C5: услуга | D5: 1 | E5: 10000000 | F5: =E5*D5 -> 10000000
A6: 2. | B6: Аналитическая обработка результатов и подготовка итогового отчёта | C6: выпуск | D6: 1 | E6: 1300000 | F6: =E6*D6 -> 1300000
B7: ИТОГО без НДС | F7: =F6+F5 -> 11300000
B8: Всего расходов с НДС | F8: =F7*1.16 -> 13108000

Sheet Разработка платформы
A1: Разработка цифровой платформы (ноябрь-декабрь)
A3: № | B3: Статьи затрат | C3: Единица измерения | D3: Количество | E3: Сумма за единицу, тенге | F3: Общая сумма, тыс.тенге
B4: Всего расходов | F4: =F6 -> 14000000
A5: 1. | B5: Первый этап разработки цифровой платформы | C5: услуга | D5: 1 | E5: 14000000 | F5: =E5*D5 -> 14000000
B6: ИТОГО без НДС | F6: =F5 -> 14000000
B7: Всего расходов с НДС | F7: =F6*1.16 -> 16240000

Sheet Канцелярия
A1: Канцелярия и бумага, ₸
A4: Группа | B4: Позиция | C4: Ед. | D4: Кол-во в месяц | E4: Цена, ₸ | F4: Сумма в месяц, ₸ | G4: Примечание
A5: Бумага и печать | B5: Бумага А4, 80 г/м² (пачка 500 л.) | C5: пачка | D5: 3.5 | E5: 3000 | F5: =D5*E5 -> 10500 | G5: ≈3 500 страниц в месяц
A6: Бумага и печать | B6: Бумага А3 (пачка 500 л.) | C6: пачка | D6: 0.25 | E6: 6500 | F6: =D6*E6 -> 1625 | G6: схемы, плакаты, раздаточные материалы
A7: Бумага и печать | B7: Бумага для флипчарта (блок) | C7: блок | D7: 0.5 | E7: 6000 | F7: =D7*E7 -> 3000 | G7: совещания, семинары
A8: Бумага и печать | B8: Плотная бумага и обложки для брошюровки | C8: компл. | D8: 0 | E8: 5000 | F8: =D8*E8 -> 0 | G8: отчёты, методические материалы
A9: Канцелярия | B9: Ручки, карандаши, маркеры, текстовыделители | C9: компл. | D9: 0 | E9: 1200 | F9: =D9*E9 -> 0 | G9: на сотрудника в офисе
A10: Канцелярия | B10: Блокноты, стикеры, закладки | C10: компл. | D10: 10 | E10: 900 | F10: =D10*E10 -> 9000 | G10: на сотрудника в офисе
B11: ИТОГО в месяц | F11: =SUM(F5:F10) -> 24125
A13: Разово при открытии офиса | D13: Кол-во | F13: Сумма, ₸
A14: Канцелярия | B14: Папки-регистраторы, скоросшиватели, файлы А4 | C14: компл. | D14: 5 | E14: 1500 | F14: =D14*E14 -> 7500 | G14: делопроизводство, договоры, кадры
A15: Канцелярия | B15: Конверты, почтовые пакеты, бумага для заметок | C15: компл. | E15: 8000 | F15: =D15*E15 -> 0 | G15: переписка с МЭПР и акиматами
A16: Канцелярия | B16: Скобы, скрепки, клей, ножницы, ножи, линейки | C16: компл. | E16: 10000 | F16: =D16*E16 -> 0 | G16: пополнение
A17: Канцелярия | B17: Степлеры, дыроколы, лотки, органайзеры (пополнение) | C17: компл. | E17: 6000 | F17: =D17*E17 -> 0
A18: Канцелярия | B18: Архивные короба и файлы для архива | C18: компл. | E18: 12000 | F18: =D18*E18 -> 0 | G18: хранение документов проекта
A19: Канцелярия | B19: Батарейки, удлинители, мелкая электрика | C19: компл. | D19: 1 | E19: 8000 | F19: =D19*E19 -> 8000 | G19: техника, пульты, микрофоны
A20: Канцелярия | B20: Датер автоматический (Trodat 4810) и краска штемпельная | C20: компл. | D20: 1 | E20: =ROUND((3676+1600)/(1+НДС),0) -> 4548 | F20: =D20*E20 -> 4548 | G20: штамп для проставления даты на входящих и исходящих. Kaspi.kz – датер Trodat 4810 ленточный русский 3 676 ₸ и краска штемпельная Trodat 28 мл 1 600 ₸, вместе 5 276 ₸ с НДС; в бюджете без НДС (÷1,16). У b2bcompany.kz датеров нет
B21: ИТОГО разово | F21: =SUM(F14:F20) -> 20048

Sheet Смета фото-видео
A1: Смета фото- и видеооборудования, ₸
A4: № | B4: Наименование | C4: Артикул | D4: Наличие / источник цены | E4: Кол-во | F4: Цена, ₸ | G4: Сумма, ₸
A5: 1. Оборудование по КП PSP Digital / Photo Plus
A6: 1 | B6: Кинокамера Canon EOS C70 Cinema Camera | C6: 5659 | D6: Предзаказ | E6: 0 | F6: 1669990 | G6: =E6*F6 -> 0
A7: 2 | B7: Объектив Canon RF 24-105mm f/4L IS USM | C7: 2584 | D7: В наличии | E7: 0 | F7: 485990 | G7: =E7*F7 -> 0
A8: 4 | B8: Электронный стабилизатор DJI RS 4 Pro Combo | C8: 6218 | D8: В наличии | E8: 0 | F8: 479990 | G8: =E8*F8 -> 0
A9: 6 | B9: Карта памяти Sony 128GB SF-G Tough UHS-II SDXC 299Mb/s | C9: 4240 | D9: В наличии | E9: 0 | F9: 104990 | G9: =E9*F9 -> 0
A10: 7 | B10: DJI Mic 3 2-Person Compact Digital Wireless Microphone System | C10: 6976 | D10: В наличии | E10: 0 | F10: 119990 | G10: =E10*F10 -> 0
A11: 9 | B11: Монопод E-Image MA600+610FH | C11: 3288 | D11: В наличии | E11: 0 | F11: 58990 | G11: =E11*F11 -> 0
A12: 10 | B12: Сумка для видеокамер E-Image OSCAR S50 (EB0925) | C12: 1756 | D12: В наличии | E12: 0 | F12: 31990 | G12: =E12*F12 -> 0
B13: Итого раздел 1 | G13: =SUM(G6:G12) -> 0
A15: 2. Аккумуляторы
A16: 2.1 | B16: Аккумулятор Canon BP-A30 для Canon EOS C70 — запасной | E16: 0 | F16: 240000 | G16: =E16*F16 -> 0
B17: Итого раздел 2 | G17: =SUM(G16:G16) -> 0
A19: 3. Дополнительное оборудование
A20: 3.3 | B20: Видеоштатив с видеоголовой | E20: 0 | F20: 250000 | G20: =E20*F20 -> 0
A21: 3.4 | B21: Внешний SSD 2 ТБ для исходников | E21: 2 | F21: 150000 | G21: =E21*F21 -> 300000
B22: Итого раздел 3 | G22: =SUM(G20:G21) -> 300000
B24: ИТОГО смета (1 + 2 + 3) | G24: =G13+G17+G22 -> 300000

Sheet Февраль 2027
A1: Февраль 2027 года: дополнение штата и расходы на новых сотрудников, ₸
A3: Должность | B3: Подразделение | C3: Работник | D3: Оклад, гросс | E3: Отчисления работодателя | F3: Стоимость в месяц
A4: Директор департамента | B4: Проектное управление и региональная координация | C4: Доскалиева | D4: 1300000 | E4: =ROUND(Ставка_СН*D4*(1-Ставка_ОПВ-Ставка_ВОСМС)+Ставка_ОПВР*D4+Ставка_СО*MIN(D4*(1-Ставка_ОПВ),Кап_СО*МЗП)+Ставка_ООСМС*MIN(D4,Кап_ООСМС*МЗП),0) -> 182890 | F4: =D4+E4 -> 1482890
A5: Главный специалист | B5: Проектное управление и региональная координация | C5: Арманов Р. | D5: 1000000 | E5: =ROUND(Ставка_СН*D5*(1-Ставка_ОПВ-Ставка_ВОСМС)+Ставка_ОПВР*D5+Ставка_СО*MIN(D5*(1-Ставка_ОПВ),Кап_СО*МЗП)+Ставка_ООСМС*MIN(D5,Кап_ООСМС*МЗП),0) -> 147550 | F5: =D5+E5 -> 1147550
A6: Ведущий специалист | B6: Проектное управление и региональная координация | C6: Мирам А. | D6: 700000 | E6: =ROUND(Ставка_СН*D6*(1-Ставка_ОПВ-Ставка_ВОСМС)+Ставка_ОПВР*D6+Ставка_СО*MIN(D6*(1-Ставка_ОПВ),Кап_СО*МЗП)+Ставка_ООСМС*MIN(D6,Кап_ООСМС*МЗП),0) -> 112210 | F6: =D6+E6 -> 812210
A7: Ведущий специалист | B7: Проектное управление и региональная координация | C7: Бекжанова Нагима | D7: 700000 | E7: =ROUND(Ставка_СН*D7*(1-Ставка_ОПВ-Ставка_ВОСМС)+Ставка_ОПВР*D7+Ставка_СО*MIN(D7*(1-Ставка_ОПВ),Кап_СО*МЗП)+Ставка_ООСМС*MIN(D7,Кап_ООСМС*МЗП),0) -> 112210 | F7: =D7+E7 -> 812210
A8: Ведущий специалист | B8: Проектное управление и региональная координация | C8: Нуржау М. | D8: 700000 | E8: =ROUND(Ставка_СН*D8*(1-Ставка_ОПВ-Ставка_ВОСМС)+Ставка_ОПВР*D8+Ставка_СО*MIN(D8*(1-Ставка_ОПВ),Кап_СО*МЗП)+Ставка_ООСМС*MIN(D8,Кап_ООСМС*МЗП),0) -> 112210 | F8: =D8+E8 -> 812210
A9: Ведущий специалист – аналитик | B9: Социологические исследования и аналитика | C9: Мукашев Дархан | D9: 700000 | E9: =ROUND(Ставка_СН*D9*(1-Ставка_ОПВ-Ставка_ВОСМС)+Ставка_ОПВР*D9+Ставка_СО*MIN(D9*(1-Ставка_ОПВ),Кап_СО*МЗП)+Ставка_ООСМС*MIN(D9,Кап_ООСМС*МЗП),0) -> 112210 | F9: =D9+E9 -> 812210
A10: Менеджер проектов | B10: Проектный офис для Центральной Азии | C10: вакансия | D10: 800000 | E10: =ROUND(Ставка_СН*D10*(1-Ставка_ОПВ-Ставка_ВОСМС)+Ставка_ОПВР*D10+Ставка_СО*MIN(D10*(1-Ставка_ОПВ),Кап_СО*МЗП)+Ставка_ООСМС*MIN(D10,Кап_ООСМС*МЗП),0) -> 123990 | F10: =D10+E10 -> 923990
A11: ИТОГО новые сотрудники (7 чел.) | D11: =SUM(D4:D10) -> 5900000 | E11: =SUM(E4:E10) -> 903270 | F11: =SUM(F4:F10) -> 6803270
A13: Разово при приходе новых сотрудников (цены без НДС)
A14: Позиция | B14: Основание | D14: Кол-во | E14: Цена | F14: Сумма
A15: Стол рабочий с подкатной тумбой (ZETA Лофт) | B15: в бюджете 20 столов на 18 новых сотрудников 2026 года – запас 2 | D15: 5 | E15: ='Оснащение и офис'!E8 -> 69708 | F15: =D15*E15 -> 348540
A16: Кресло рабочее (МИ-6 Z) | B16: в бюджете 26 кресел на 18 сотрудников и 7 аутсорсеров – запас 1 | D16: 6 | E16: ='Оснащение и офис'!E9 -> 14750 | F16: =D16*E16 -> 88500
A17: Сетевые фильтры на рабочие места | B17: по 1 на нового сотрудника | D17: 7 | E17: ='Оснащение и офис'!E37 -> 3550 | F17: =D17*E17 -> 24850
A18: Сборка, доставка и подъём мебели | B18: доля от стоимости столов и кресел (лист «Параметры») | F18: =ROUND((F15+F16)*Сборка_мебели_проц,0) -> 43704
A19: ИТОГО оснащение | F19: =SUM(F15:F18) -> 505594
A21: Ежемесячно и прочее
A22: Microsoft 365 для новых сотрудников, в месяц | D22: 7 | E22: ='Оснащение и офис'!E68 -> 7000 | F22: =D22*E22 -> 49000
A23: ОСНС: годовой полис на новых сотрудников | B23: 0,29% годового ФОТ, как в «Параметрах» | F23: =ROUND(0.29%*12*D11,-3) -> 205000
A24: Командировки новых сотрудников, в месяц | B24: нормы листа «Командировки»: проектное управление – 6 поездок в год, социология – 3 в год и 3 выезда в месяц | F24: =5*6/12*Поездка_РК+1*(3/12*Поездка_РК+3*Поездка_местн) -> 596062.5
A25: Первоочередные проекты | B25: среднемесячно за ноябрь 2026 – январь 2027 | F25: =Проекты!G13/3 -> 29078107
